{"nm":"Main Scene","ddd":0,"h":968,"w":2101.2800255150773,"meta":{"g":"@lottiefiles/creator 1.86.1"},"layers":[{"ty":4,"nm":"l hand","sr":1,"st":0,"op":180,"ip":0,"hd":false,"ddd":0,"bm":0,"hasMask":false,"ao":0,"ks":{"a":{"a":0,"k":[201.078,202.755,0],"ix":1},"s":{"a":0,"k":[100,100,100],"ix":6},"sk":{"a":0,"k":0},"p":{"a":0,"k":[201.078,202.755,0],"ix":2},"r":{"a":1,"k":[{"o":{"x":0.333,"y":0},"i":{"x":0.667,"y":1},"s":[-10],"t":0},{"o":{"x":0.333,"y":0},"i":{"x":0.667,"y":1},"s":[7],"t":20},{"o":{"x":0.333,"y":0},"i":{"x":0.833,"y":1},"s":[7],"t":30},{"o":{"x":0.167,"y":0},"i":{"x":0.667,"y":1},"s":[13],"t":53},{"o":{"x":0.333,"y":0},"i":{"x":0.833,"y":1},"s":[3],"t":77},{"o":{"x":0.167,"y":0},"i":{"x":0.667,"y":1},"s":[3],"t":90},{"s":[-10],"t":110}],"ix":10},"sa":{"a":0,"k":0},"o":{"a":0,"k":100,"ix":11}},"shapes":[{"ty":"gr","bm":0,"hd":false,"mn":"ADBE Vector Group","nm":"Group 3","ix":1,"cix":2,"np":1,"it":[{"ty":"gr","bm":0,"hd":false,"mn":"ADBE Vector Group","nm":"Group 2","ix":1,"cix":2,"np":3,"it":[{"ty":"sh","bm":0,"hd":false,"mn":"ADBE Vector Shape - Group","nm":"Path 1","ix":1,"d":1,"ks":{"a":0,"k":{"c":true,"i":[[0,0],[2.953,9.427],[10.564,-0.359],[11.925,-6.7],[-10.812,-92.439],[-13.8,-20.999],[0,0],[0,0],[0,0]],"o":[[-4.83,-12.039],[-20.547,-57.323],[-1.627,0.055],[-9.011,5.063],[3.897,33.316],[13.8,20.999],[0,0],[0,0],[0,0]],"v":[[20.468,-3.211],[9.185,-35.927],[-34.985,-157.181],[-51.85,-152.313],[-76.05,-19.811],[-52.662,45.251],[7.434,103.019],[42.864,125.601],[112.652,57.073]]},"ix":2}},{"ty":"st","bm":0,"hd":false,"mn":"ADBE Vector Graphic - Stroke","nm":"Stroke 1","lc":1,"lj":1,"ml":4,"o":{"a":0,"k":100,"ix":4},"w":{"a":0,"k":4,"ix":5},"c":{"a":0,"k":[0.1608,0.1725,0.3373],"ix":3}},{"ty":"fl","bm":0,"hd":false,"mn":"ADBE Vector Graphic - Fill","nm":"Fill 1","c":{"a":0,"k":[1,1,1],"ix":4},"r":1,"o":{"a":0,"k":100,"ix":5}},{"ty":"tr","a":{"a":0,"k":[0,0],"ix":1},"s":{"a":0,"k":[100,100],"ix":3},"sk":{"a":0,"k":0,"ix":4},"p":{"a":0,"k":[238.861,358.751],"ix":2},"r":{"a":0,"k":0,"ix":6},"sa":{"a":0,"k":0,"ix":5},"o":{"a":0,"k":100,"ix":7}}]},{"ty":"tr","a":{"a":0,"k":[238.861,358.751],"ix":1},"s":{"a":0,"k":[100,100],"ix":3},"sk":{"a":0,"k":0,"ix":4},"p":{"a":0,"k":[238.861,358.751],"ix":2},"r":{"a":0,"k":0,"ix":6},"sa":{"a":0,"k":0,"ix":5},"o":{"a":0,"k":100,"ix":7}}]},{"ty":"gr","bm":0,"hd":false,"mn":"ADBE Vector Group","nm":"Group 4","ix":2,"cix":2,"np":2,"it":[{"ty":"gr","bm":0,"hd":false,"mn":"ADBE Vector Group","nm":"Group 1","ix":1,"cix":2,"np":3,"it":[{"ty":"sh","bm":0,"hd":false,"mn":"ADBE Vector Shape - Group","nm":"Path 1","ix":1,"d":1,"ks":{"a":0,"k":{"c":true,"i":[[0,0],[-3.613,1.299],[-0.015,0.083],[-0.861,0],[-1.87,2.191],[0.006,0.035],[-1.072,0.022],[-0.913,1.514],[0.013,0.026],[-1.164,0.194],[-1.877,5.743],[22.076,8.954],[0,0],[0,0],[0,0],[-0.022,-0.686],[-1.031,-2.184],[-8.315,-3.051],[-7.725,-0.55],[1.203,-1.028]],"o":[[3.152,0.429],[5.533,-1.992],[0.149,-0.848],[4.541,0],[2.283,-2.675],[-0.169,-1.064],[3.728,-0.074],[1.117,-1.85],[-0.539,-1.076],[0.086,-0.015],[-0.212,-3.639],[0,0],[0,0],[0,0],[0.629,0.273],[0.083,2.607],[3.408,7.224],[7.081,2.6],[1.578,0.112],[0,0]],"v":[[16.446,47.773],[27.866,47.177],[34.905,36.925],[36.652,35.455],[46.315,32.153],[48.102,25.889],[49.818,23.838],[56.912,21.41],[56.723,16.908],[58.013,14.356],[68.499,7.105],[22.441,-17.571],[-41.362,-47.63],[-67.687,-5.56],[-23.898,13.423],[-22.832,14.993],[-21.153,22.213],[-1.576,35.37],[20.737,40.118],[21.762,43.234]]},"ix":2}},{"ty":"sh","bm":0,"hd":false,"mn":"ADBE Vector Shape - Group","nm":"Path 2","ix":2,"d":1,"ks":{"a":0,"k":{"c":true,"i":[[4.967,1.246],[-1.093,0.935],[0,0],[6.1,2.239],[4.029,8.539],[0.211,2.671],[0,0],[-0.574,0.914],[0,0],[-0.811,-0.38],[0,0],[-11.965,-5.819],[0.978,-2.991],[3.235,-0.924],[7.633,-0.686],[9.096,-0.446],[5.861,-2.11]],"o":[[-1.392,-0.353],[0,0],[-6.578,-0.788],[-8.619,-3.163],[-1.086,-2.302],[0,0],[-0.998,-0.432],[0,0],[0.477,-0.76],[0,0],[0.035,0.011],[22.401,10.893],[-1.887,5.772],[1.201,4.938],[-0.245,6.243],[-0.782,2.927],[-4.918,1.77]],"v":[[12.025,50.564],[11.309,47.497],[16.28,43.253],[-2.797,38.699],[-24.359,23.726],[-26.312,16.24],[-70.988,-3.127],[-71.785,-5.693],[-43.533,-50.843],[-41.275,-51.507],[23.863,-20.818],[48.262,-9.947],[71.869,8.206],[60.62,17.376],[51.686,27.287],[38.07,38.967],[29.068,50.513]]},"ix":2}},{"ty":"fl","bm":0,"hd":false,"mn":"ADBE Vector Graphic - Fill","nm":"Fill 1","c":{"a":0,"k":[0.1608,0.1725,0.3373],"ix":4},"r":1,"o":{"a":0,"k":100,"ix":5}},{"ty":"tr","a":{"a":0,"k":[0,0],"ix":1},"s":{"a":0,"k":[100,100],"ix":3},"sk":{"a":0,"k":0,"ix":4},"p":{"a":0,"k":[359.665,449.765],"ix":2},"r":{"a":0,"k":0,"ix":6},"sa":{"a":0,"k":0,"ix":5},"o":{"a":0,"k":100,"ix":7}}]},{"ty":"gr","bm":0,"hd":false,"mn":"ADBE Vector Group","nm":"Group 2","ix":2,"cix":2,"np":2,"it":[{"ty":"sh","bm":0,"hd":false,"mn":"ADBE Vector Shape - Group","nm":"Path 1","ix":1,"d":1,"ks":{"a":0,"k":{"c":true,"i":[[-9.417,15.05],[0,0],[2.244,-6.865],[0,0],[13.202,-0.264],[15.05,0],[6.601,-2.376],[0,0],[0,0],[5.203,1.91],[3.644,7.723],[0.064,2.002],[15.226,6.601]],"o":[[0,0],[0,0],[-2.244,6.865],[0,0],[0,0],[0,0],[-6.601,2.376],[0,0],[-9.846,-0.702],[-8.954,-3.286],[-1.432,-3.035],[-15.226,-6.601],[9.417,-15.05]],"v":[[-42.019,-49.903],[23.12,-19.213],[70.196,7.657],[58.314,16.106],[49.865,25.611],[36.664,37.229],[28.479,48.846],[12.472,48.846],[20.623,41.887],[-2.174,37.037],[-22.744,22.971],[-24.592,15.05],[-70.27,-4.753]]},"ix":2}},{"ty":"fl","bm":0,"hd":false,"mn":"ADBE Vector Graphic - Fill","nm":"Fill 1","c":{"a":0,"k":[1,1,1],"ix":4},"r":1,"o":{"a":0,"k":100,"ix":5}},{"ty":"tr","a":{"a":0,"k":[0,0],"ix":1},"s":{"a":0,"k":[100,100],"ix":3},"sk":{"a":0,"k":0,"ix":4},"p":{"a":0,"k":[359.653,449.764],"ix":2},"r":{"a":0,"k":0,"ix":6},"sa":{"a":0,"k":0,"ix":5},"o":{"a":0,"k":100,"ix":7}}]},{"ty":"tr","a":{"a":0,"k":[359.653,449.764],"ix":1},"s":{"a":0,"k":[100,100],"ix":3},"sk":{"a":0,"k":0,"ix":4},"p":{"a":0,"k":[359.653,449.764],"ix":2},"r":{"a":0,"k":0,"ix":6},"sa":{"a":0,"k":0,"ix":5},"o":{"a":0,"k":100,"ix":7}}]}],"ind":1,"parent":4},{"ty":4,"nm":"glass","sr":1,"st":0,"op":180,"ip":0,"hd":false,"ddd":0,"bm":0,"hasMask":false,"ao":0,"ks":{"a":{"a":0,"k":[411.872,447.798,0],"ix":1},"s":{"a":0,"k":[100,100,100],"ix":6},"sk":{"a":0,"k":0},"p":{"a":0,"k":[411.872,447.798,0],"ix":2},"r":{"a":0,"k":0,"ix":10},"sa":{"a":0,"k":0},"o":{"a":0,"k":100,"ix":11}},"shapes":[{"ty":"gr","bm":0,"hd":false,"mn":"ADBE Vector Group","nm":"Group 1","ix":1,"cix":2,"np":2,"it":[{"ty":"gr","bm":0,"hd":false,"mn":"ADBE Vector Group","nm":"Group 1","ix":1,"cix":2,"np":3,"it":[{"ty":"sh","bm":0,"hd":false,"mn":"ADBE Vector Shape - Group","nm":"Path 1","ix":1,"d":1,"ks":{"a":0,"k":{"c":true,"i":[[0,0],[0,0],[0.15,6.784],[-1.189,-0.786],[-1.114,0.444],[-0.308,1.319],[-0.966,-1.014],[-0.935,0.227],[-0.454,1.527],[-0.946,-0.344],[-1.212,-0.05],[-1.882,1.826],[4.424,20.522],[2.785,0.879],[0.525,-0.209],[-1.484,-9.758],[0.958,-0.158],[0.168,0.955],[0.484,0.464],[0.672,-0.501],[-0.413,-5.864],[-0.718,-2.52],[0.918,-0.286],[0.308,0.91],[0.332,1.181],[2.816,0],[-3.36,-13.706],[0.892,-0.28],[0.336,0.872],[3.437,1.155],[0.203,-0.125],[-6.477,-14.209],[0.553,-0.52]],"o":[[0,0],[6.197,1.593],[-0.034,-1.428],[1.564,1.029],[2.336,-0.932],[0.321,-1.375],[0.749,0.783],[1.67,-0.402],[0.297,-0.991],[0.685,0.249],[0.939,0.035],[2.34,-2.274],[-1.199,-5.601],[-0.474,-0.149],[-2.91,1.151],[0.145,0.96],[-0.961,0.15],[-2.602,-14.751],[-1.053,-0.312],[-0.75,0.56],[0.566,8.067],[0.263,0.924],[-0.923,0.284],[-0.399,-1.175],[-2.781,-8.292],[-1.953,1.172],[0.222,0.909],[-0.889,0.28],[-2.818,-7.309],[-0.385,-0.129],[-2.48,1.536],[0.315,0.692],[0,0]],"v":[[-25.411,28.293],[-16.874,30.986],[-4.742,22.182],[-1.996,20.662],[1.984,21.528],[6.033,15.302],[9.04,14.48],[11.819,15.924],[15.423,10.714],[17.729,9.552],[21.671,10.509],[26.031,8.386],[22.095,-19.411],[16.98,-31.181],[15.237,-31.223],[13.608,-9.533],[12.142,-7.517],[10.109,-8.958],[4.421,-27.272],[1.503,-26.769],[0.358,-18.95],[3.611,-3.119],[2.434,-0.941],[0.228,-2.063],[-0.869,-5.597],[-10.579,-21.734],[-7.882,6.699],[-9.073,8.812],[-11.258,7.758],[-23.027,-11.519],[-23.825,-11.466],[-16.32,18.09],[-16.718,20.117]]},"ix":2}},{"ty":"sh","bm":0,"hd":false,"mn":"ADBE Vector Shape - Group","nm":"Path 2","ix":2,"d":1,"ks":{"a":0,"k":{"c":true,"i":[[6.131,0],[12.053,3.799],[-0.986,0.926],[0,0],[-6.444,3.991],[-2.652,-4.466],[-0.546,0.697],[-1.148,0],[-2.113,-3.318],[-2.176,1.625],[-2.084,-0.779],[-1.526,-3.557],[-2.772,1.096],[-0.672,-0.211],[-1.229,-5.764],[4.079,-3.963],[1.649,0.074],[1.001,0.286],[4.129,2.411],[4.635,1.561]],"o":[[-2.87,0],[-1.29,-0.406],[0,0],[-3.574,-8.018],[4.421,-2.737],[-1.884,-12.972],[0.738,-0.941],[2.744,0],[-0.317,-5.627],[1.783,-1.329],[0.701,0.262],[0.498,-4.196],[1.695,-0.67],[5.242,1.654],[4.531,21.118],[-2.788,2.704],[-1.054,-0.043],[-1.944,4.597],[-1.907,4.62],[-1.157,6.271]],"v":[[-14.017,34.885],[-29.361,30.764],[-30.042,27.783],[-20.069,18.401],[-25.691,-14.48],[-14.167,-6.588],[-13.461,-23.842],[-10.579,-25.279],[-3.229,-19.488],[-0.618,-29.609],[5.843,-30.533],[9.366,-25.723],[13.935,-34.519],[18.044,-34.563],[25.683,-19.588],[28.502,10.928],[21.523,14.051],[18.201,13.424],[8.636,18.686],[-1.422,24.883]]},"ix":2}},{"ty":"fl","bm":0,"hd":false,"mn":"ADBE Vector Graphic - Fill","nm":"Fill 1","c":{"a":0,"k":[0,0.2353,0.5922],"ix":4},"r":1,"o":{"a":0,"k":100,"ix":5}},{"ty":"tr","a":{"a":0,"k":[0,0],"ix":1},"s":{"a":0,"k":[100,100],"ix":3},"sk":{"a":0,"k":0,"ix":4},"p":{"a":0,"k":[467.91,419.026],"ix":2},"r":{"a":0,"k":0,"ix":6},"sa":{"a":0,"k":0,"ix":5},"o":{"a":0,"k":100,"ix":7}}]},{"ty":"gr","bm":0,"hd":false,"mn":"ADBE Vector Group","nm":"Group 2","ix":2,"cix":2,"np":2,"it":[{"ty":"sh","bm":0,"hd":false,"mn":"ADBE Vector Shape - Group","nm":"Path 1","ix":1,"d":1,"ks":{"a":0,"k":{"c":true,"i":[[3.807,1.201],[-3.632,3.416],[-5.985,3.707],[0,0],[-6.535,0],[0,0],[0.276,3.931],[-1.563,1.167],[-1.645,-0.615],[-3.235,-18.336],[-8.287,-2.614],[-1.413,-6.589],[3.254,-3.16],[2.847,0.118],[0,0],[6.145,6.438],[7.998,5.267],[7.419,1.918]],"o":[[3.632,-3.416],[0,0],[5.985,-3.707],[0,0],[6.535,0],[-2.262,-6.662],[-0.415,-5.904],[1.201,-0.897],[0,0],[-1.295,-8.513],[3.881,1.224],[4.398,20.508],[-0.551,0.535],[-1.759,-0.073],[0,0],[0,0],[0.185,7.978],[-3.807,-1.201]],"v":[[-28.829,29.081],[-17.933,18.832],[-24.759,-12.966],[-9.605,7.127],[-10.58,-23.5],[1.905,-2.627],[-1.412,-18.819],[0.442,-28.182],[5.221,-28.865],[11.854,-9.259],[17.511,-32.864],[23.949,-19.209],[27.266,9.663],[21.596,12.287],[17.121,11.224],[7.757,15.711],[-2.972,22.149],[-17.408,32.683]]},"ix":2}},{"ty":"fl","bm":0,"hd":false,"mn":"ADBE Vector Graphic - Fill","nm":"Fill 1","c":{"a":0,"k":[0,0.2353,0.5922],"ix":4},"r":1,"o":{"a":0,"k":100,"ix":5}},{"ty":"tr","a":{"a":0,"k":[0,0],"ix":1},"s":{"a":0,"k":[100,100],"ix":3},"sk":{"a":0,"k":0,"ix":4},"p":{"a":0,"k":[467.911,419.019],"ix":2},"r":{"a":0,"k":0,"ix":6},"sa":{"a":0,"k":0,"ix":5},"o":{"a":0,"k":100,"ix":7}}]},{"ty":"tr","a":{"a":0,"k":[467.911,419.019],"ix":1},"s":{"a":0,"k":[100,100],"ix":3},"sk":{"a":0,"k":0,"ix":4},"p":{"a":0,"k":[467.911,419.019],"ix":2},"r":{"a":0,"k":0,"ix":6},"sa":{"a":0,"k":0,"ix":5},"o":{"a":0,"k":100,"ix":7}}]},{"ty":"gr","bm":0,"hd":false,"mn":"ADBE Vector Group","nm":"Group 2","ix":2,"cix":2,"np":3,"it":[{"ty":"sh","bm":0,"hd":false,"mn":"ADBE Vector Shape - Group","nm":"Path 1","ix":1,"d":1,"ks":{"a":0,"k":{"c":true,"i":[[45.68,-37.052],[37.052,45.68],[-45.68,37.052],[-37.052,-45.68]],"o":[[-45.68,37.052],[-37.052,-45.679],[45.68,-37.052],[37.052,45.68]],"v":[[67.197,82.843],[-82.843,67.197],[-67.197,-82.843],[82.843,-67.197]]},"ix":2}},{"ty":"sh","bm":0,"hd":false,"mn":"ADBE Vector Shape - Group","nm":"Path 2","ix":2,"d":1,"ks":{"a":0,"k":{"c":true,"i":[[50.311,62.025],[62.026,-50.311],[-50.311,-62.026],[-62.025,50.311]],"o":[[-50.311,-62.026],[-62.025,50.311],[50.311,62.025],[62.025,-50.311]],"v":[[112.487,-91.242],[-91.242,-112.487],[-112.487,91.242],[91.242,112.487]]},"ix":2}},{"ty":"fl","bm":0,"hd":false,"mn":"ADBE Vector Graphic - Fill","nm":"Fill 1","c":{"a":0,"k":[0,0.2353,0.5922],"ix":4},"r":1,"o":{"a":0,"k":100,"ix":5}},{"ty":"tr","a":{"a":0,"k":[0,0],"ix":1},"s":{"a":0,"k":[100,100],"ix":3},"sk":{"a":0,"k":0,"ix":4},"p":{"a":0,"k":[593.692,287.48],"ix":2},"r":{"a":0,"k":0,"ix":6},"sa":{"a":0,"k":0,"ix":5},"o":{"a":0,"k":100,"ix":7}}]},{"ty":"gr","bm":0,"hd":false,"mn":"ADBE Vector Group","nm":"Group 3","ix":3,"cix":2,"np":2,"it":[{"ty":"sh","bm":0,"hd":false,"mn":"ADBE Vector Shape - Group","nm":"Path 1","ix":1,"d":1,"ks":{"a":0,"k":{"c":true,"i":[[9.408,11.598],[-14.124,10.878],[0,0],[-7.055,-8.698],[8.807,-7.519],[0,0]],"o":[[-9.96,-12.279],[0,0],[9.209,-7.093],[7.083,8.732],[0,0],[-14.439,12.328]],"v":[[-104.058,84.213],[-93.447,41.92],[75.065,-87.867],[104.327,-84.816],[101.275,-55.554],[-60.486,82.556]]},"ix":2}},{"ty":"fl","bm":0,"hd":false,"mn":"ADBE Vector Graphic - Fill","nm":"Fill 1","c":{"a":0,"k":[0,0.2353,0.5922],"ix":4},"r":1,"o":{"a":0,"k":100,"ix":5}},{"ty":"tr","a":{"a":0,"k":[0,0],"ix":1},"s":{"a":0,"k":[100,100],"ix":3},"sk":{"a":0,"k":0,"ix":4},"p":{"a":0,"k":[406.146,444.512],"ix":2},"r":{"a":0,"k":0,"ix":6},"sa":{"a":0,"k":0,"ix":5},"o":{"a":0,"k":100,"ix":7}}]}],"ind":2,"parent":1},{"ty":4,"nm":"head","sr":1,"st":0,"op":180,"ip":0,"hd":false,"ddd":0,"bm":0,"hasMask":false,"ao":0,"ks":{"a":{"a":0,"k":[301.873,177.627,0],"ix":1},"s":{"a":0,"k":[100,100,100],"ix":6},"sk":{"a":0,"k":0},"p":{"a":0,"k":[301.873,177.627,0],"ix":2},"r":{"a":1,"k":[{"o":{"x":0.333,"y":0},"i":{"x":0.667,"y":1},"s":[0],"t":0},{"o":{"x":0.333,"y":0},"i":{"x":0.667,"y":1},"s":[8],"t":20},{"o":{"x":0.333,"y":0},"i":{"x":0.833,"y":1},"s":[8],"t":30},{"o":{"x":0.167,"y":0},"i":{"x":0.667,"y":1},"s":[0],"t":53},{"o":{"x":0.333,"y":0},"i":{"x":0.667,"y":1},"s":[8],"t":77},{"o":{"x":0.333,"y":0},"i":{"x":0.667,"y":1},"s":[8],"t":90},{"s":[0],"t":110}],"ix":10},"sa":{"a":0,"k":0},"o":{"a":0,"k":100,"ix":11}},"shapes":[{"ty":"gr","bm":0,"hd":false,"mn":"ADBE Vector Group","nm":"Group 1","ix":1,"cix":2,"np":1,"it":[{"ty":"gr","bm":0,"hd":false,"mn":"ADBE Vector Group","nm":"Group 1","ix":1,"cix":2,"np":2,"it":[{"ty":"sh","bm":0,"hd":false,"mn":"ADBE Vector Shape - Group","nm":"Path 1","ix":1,"d":1,"ks":{"a":0,"k":{"c":true,"i":[[-5.545,-12.85],[-18.192,-24.071],[7.685,11.618],[9.726,-7.393]],"o":[[0,0],[0,0],[-7.685,-11.618],[-9.726,7.393]],"v":[[-29.861,24.338],[32.214,24.338],[34.987,-15.883],[-33.073,-18.524]]},"ix":2}},{"ty":"fl","bm":0,"hd":false,"mn":"ADBE Vector Graphic - Fill","nm":"Fill 1","c":{"a":0,"k":[0,0.2353,0.5922],"ix":4},"r":1,"o":{"a":0,"k":100,"ix":5}},{"ty":"tr","a":{"a":0,"k":[0,0],"ix":1},"s":{"a":0,"k":[100,100],"ix":3},"sk":{"a":0,"k":0,"ix":4},"p":{"a":0,"k":[0,0],"ix":2},"r":{"a":0,"k":0,"ix":6},"sa":{"a":0,"k":0,"ix":5},"o":{"a":0,"k":100,"ix":7}}]},{"ty":"tr","a":{"a":0,"k":[0,0],"ix":1},"s":{"a":0,"k":[100,100],"ix":3},"sk":{"a":0,"k":0,"ix":4},"p":{"a":0,"k":[302.873,138.772],"ix":2},"r":{"a":0,"k":0,"ix":6},"sa":{"a":0,"k":0,"ix":5},"o":{"a":0,"k":100,"ix":7}}]},{"ty":"gr","bm":0,"hd":false,"mn":"ADBE Vector Group","nm":"Group 2","ix":2,"cix":2,"np":1,"it":[{"ty":"gr","bm":0,"hd":false,"mn":"ADBE Vector Group","nm":"Group 1","ix":1,"cix":2,"np":2,"it":[{"ty":"sh","bm":0,"hd":false,"mn":"ADBE Vector Shape - Group","nm":"Path 1","ix":1,"d":1,"ks":{"a":0,"k":{"c":true,"i":[[-3.097,-0.608],[-3.36,-4.665],[-6.669,9.634],[-11.265,1.408],[0,0],[7.128,11.2],[11.391,3.659],[10.687,-14.254],[-1.035,-2.64]],"o":[[0,0],[3.36,4.665],[6.669,-9.634],[11.265,-1.408],[0.758,-1.269],[-0.817,-1.285],[-8.166,-2.623],[-7.782,10.38],[0.224,-3.047]],"v":[[-24.954,11.094],[-19.304,15.226],[0.338,4.136],[18.82,6.248],[28.599,21.21],[31.318,-6.953],[16.18,-16.107],[-30.114,-13.29],[-30.818,15.754]]},"ix":2}},{"ty":"fl","bm":0,"hd":false,"mn":"ADBE Vector Graphic - Fill","nm":"Fill 1","c":{"a":0,"k":[0.1608,0.1725,0.3373],"ix":4},"r":1,"o":{"a":0,"k":100,"ix":5}},{"ty":"tr","a":{"a":0,"k":[0,0],"ix":1},"s":{"a":0,"k":[100,100],"ix":3},"sk":{"a":0,"k":0,"ix":4},"p":{"a":0,"k":[0,0],"ix":2},"r":{"a":0,"k":0,"ix":6},"sa":{"a":0,"k":0,"ix":5},"o":{"a":0,"k":100,"ix":7}}]},{"ty":"tr","a":{"a":0,"k":[0,0],"ix":1},"s":{"a":0,"k":[100,100],"ix":3},"sk":{"a":0,"k":0,"ix":4},"p":{"a":0,"k":[303.831,147.356],"ix":2},"r":{"a":0,"k":0,"ix":6},"sa":{"a":0,"k":0,"ix":5},"o":{"a":0,"k":100,"ix":7}}]},{"ty":"gr","bm":0,"hd":false,"mn":"ADBE Vector Group","nm":"Group 3","ix":3,"cix":2,"np":2,"it":[{"ty":"gr","bm":0,"hd":false,"mn":"ADBE Vector Group","nm":"Group 1","ix":1,"cix":2,"np":3,"it":[{"ty":"sh","bm":0,"hd":false,"mn":"ADBE Vector Shape - Group","nm":"Path 1","ix":1,"d":1,"ks":{"a":0,"k":{"c":true,"i":[[-5.386,-4.694],[-1.668,-0.217],[-0.205,-0.662],[-4.036,-3.471],[-8.792,-0.296],[-1.406,21.464],[0,0],[2.798,3.222],[8.372,-2.602],[4.15,-5.495],[0.647,-2.769],[0.939,0.193]],"o":[[1.401,1.221],[0.687,0.09],[2.189,7.081],[4.108,3.535],[10.814,0.396],[0,0],[0.279,-4.243],[-8.191,-9.43],[-0.069,0.022],[-1.528,2.024],[-0.218,0.935],[-6.671,-1.367]],"v":[[-24.465,-0.227],[-19.705,2.004],[-18.241,3.238],[-8.811,18.341],[12.293,28.144],[27.535,-6.188],[27.535,-6.188],[23.627,-17.763],[-4.683,-27.194],[-15.879,-19.457],[-19.156,-12.234],[-21.236,-10.9]]},"ix":2}},{"ty":"sh","bm":0,"hd":false,"mn":"ADBE Vector Shape - Group","nm":"Path 2","ix":2,"d":1,"ks":{"a":0,"k":{"c":true,"i":[[14.603,0],[6.582,5.663],[2.399,7.126],[-4.769,5.471],[-2.787,-0.145],[-1.533,2.031],[-0.33,0.102],[-9.086,-10.461],[0.339,-5.181]],"o":[[-8.683,0],[-4.418,-3.8],[-8.161,-1.93],[1.666,-1.911],[0.786,-2.625],[4.829,-6.395],[9.795,-3.049],[3.415,3.932],[-1.249,19.07]],"v":[[12.768,31.698],[-11.124,21.028],[-21.297,5.312],[-29.162,-11.831],[-22.197,-14.585],[-18.708,-21.593],[-5.736,-30.578],[26.303,-20.088],[31.073,-5.956]]},"ix":2}},{"ty":"fl","bm":0,"hd":false,"mn":"ADBE Vector Graphic - Fill","nm":"Fill 1","c":{"a":0,"k":[0.1608,0.1725,0.3373],"ix":4},"r":1,"o":{"a":0,"k":100,"ix":5}},{"ty":"tr","a":{"a":0,"k":[0,0],"ix":1},"s":{"a":0,"k":[100,100],"ix":3},"sk":{"a":0,"k":0,"ix":4},"p":{"a":0,"k":[303.088,171.122],"ix":2},"r":{"a":0,"k":0,"ix":6},"sa":{"a":0,"k":0,"ix":5},"o":{"a":0,"k":100,"ix":7}}]},{"ty":"gr","bm":0,"hd":false,"mn":"ADBE Vector Group","nm":"Group 2","ix":2,"cix":2,"np":2,"it":[{"ty":"sh","bm":0,"hd":false,"mn":"ADBE Vector Shape - Group","nm":"Path 1","ix":1,"d":1,"ks":{"a":0,"k":{"c":true,"i":[[-1.35,20.62],[3.081,3.547],[6.195,2.03],[7.414,-2.307],[4.451,-5.895],[0.685,-2.932],[1.639,-1.881],[-7.194,-0.94],[-4.344,-3.737],[-9.136,-0.307]],"o":[[0.307,-4.688],[-2.991,-3.444],[-2.828,-0.926],[-0.378,0.118],[-1.718,2.276],[-2.682,-0.548],[-4.172,4.787],[2.269,7.329],[4.712,4.054],[12.817,0.431]],"v":[[29.315,-6.058],[24.977,-18.911],[11.296,-28.239],[-5.198,-28.872],[-17.282,-20.51],[-20.871,-12.622],[-27.814,-10.652],[-19.924,3.776],[-9.957,19.7],[12.244,29.931]]},"ix":2}},{"ty":"fl","bm":0,"hd":false,"mn":"ADBE Vector Graphic - Fill","nm":"Fill 1","c":{"a":0,"k":[1,1,1],"ix":4},"r":1,"o":{"a":0,"k":100,"ix":5}},{"ty":"tr","a":{"a":0,"k":[0,0],"ix":1},"s":{"a":0,"k":[100,100],"ix":3},"sk":{"a":0,"k":0,"ix":4},"p":{"a":0,"k":[303.077,171.108],"ix":2},"r":{"a":0,"k":0,"ix":6},"sa":{"a":0,"k":0,"ix":5},"o":{"a":0,"k":100,"ix":7}}]},{"ty":"tr","a":{"a":0,"k":[303.077,171.108],"ix":1},"s":{"a":0,"k":[100,100],"ix":3},"sk":{"a":0,"k":0,"ix":4},"p":{"a":0,"k":[303.077,171.108],"ix":2},"r":{"a":0,"k":0,"ix":6},"sa":{"a":0,"k":0,"ix":5},"o":{"a":0,"k":100,"ix":7}}]}],"ind":3,"parent":4},{"ty":4,"nm":"body","sr":1,"st":0,"op":180,"ip":0,"hd":false,"ddd":0,"bm":0,"hasMask":false,"ao":0,"ks":{"a":{"a":0,"k":[288.556,406.262,0],"ix":1},"s":{"a":0,"k":[100,100,100],"ix":6},"sk":{"a":0,"k":0},"p":{"a":1,"k":[{"o":{"x":0.333,"y":0},"i":{"x":0.667,"y":1},"s":[801.6383196939848,373.262],"t":0},{"o":{"x":0.167,"y":0.167},"i":{"x":0.833,"y":0.833},"s":[826.6383196939848,392.262],"t":20},{"o":{"x":0.333,"y":0},"i":{"x":0.667,"y":1},"s":[826.6383196939848,392.262],"t":30},{"o":{"x":0.333,"y":0},"i":{"x":0.667,"y":1},"s":[815.6383196939848,390.262],"t":53},{"o":{"x":0.167,"y":0.167},"i":{"x":0.833,"y":0.833},"s":[826.6383196939848,392.262],"t":77},{"o":{"x":0.333,"y":0},"i":{"x":0.667,"y":1},"s":[826.6383196939848,392.262],"t":90},{"s":[801.6383196939848,373.262],"t":110}],"ix":2},"r":{"a":1,"k":[{"o":{"x":0.333,"y":0},"i":{"x":0.667,"y":1},"s":[-3],"t":0},{"o":{"x":0.333,"y":0},"i":{"x":0.667,"y":1},"s":[5],"t":20},{"o":{"x":0.333,"y":0},"i":{"x":0.833,"y":1},"s":[5],"t":30},{"o":{"x":0.167,"y":0},"i":{"x":0.667,"y":1},"s":[-3],"t":53},{"o":{"x":0.333,"y":0},"i":{"x":0.833,"y":1},"s":[5],"t":77},{"o":{"x":0.167,"y":0},"i":{"x":0.667,"y":1},"s":[5],"t":90},{"s":[-3],"t":110}],"ix":10},"sa":{"a":0,"k":0},"o":{"a":0,"k":100,"ix":11}},"shapes":[{"ty":"gr","bm":0,"hd":false,"mn":"ADBE Vector Group","nm":"Group 1","ix":1,"cix":2,"np":1,"it":[{"ty":"gr","bm":0,"hd":false,"mn":"ADBE Vector Group","nm":"Group 1","ix":1,"cix":2,"np":2,"it":[{"ty":"sh","bm":0,"hd":false,"mn":"ADBE Vector Shape - Group","nm":"Path 1","ix":1,"d":1,"ks":{"a":0,"k":{"c":true,"i":[[-0.503,0.089],[-0.171,-0.963],[0.963,-0.173]],"o":[[0.971,-0.171],[0.172,0.963],[-0.114,0.021]],"v":[[-19.352,6.106],[-17.298,7.54],[-18.73,9.596]]},"ix":2}},{"ty":"fl","bm":0,"hd":false,"mn":"ADBE Vector Graphic - Fill","nm":"Fill 1","c":{"a":0,"k":[0.1608,0.1725,0.3373],"ix":4},"r":1,"o":{"a":0,"k":100,"ix":5}},{"ty":"tr","a":{"a":0,"k":[0,0],"ix":1},"s":{"a":0,"k":[100,100],"ix":3},"sk":{"a":0,"k":0,"ix":4},"p":{"a":0,"k":[0,0],"ix":2},"r":{"a":0,"k":0,"ix":6},"sa":{"a":0,"k":0,"ix":5},"o":{"a":0,"k":100,"ix":7}}]},{"ty":"tr","a":{"a":0,"k":[0,0],"ix":1},"s":{"a":0,"k":[100,100],"ix":3},"sk":{"a":0,"k":0,"ix":4},"p":{"a":0,"k":[394.071,376.758],"ix":2},"r":{"a":0,"k":0,"ix":6},"sa":{"a":0,"k":0,"ix":5},"o":{"a":0,"k":100,"ix":7}}]},{"ty":"gr","bm":0,"hd":false,"mn":"ADBE Vector Group","nm":"Group 2","ix":2,"cix":2,"np":1,"it":[{"ty":"gr","bm":0,"hd":false,"mn":"ADBE Vector Group","nm":"Group 1","ix":1,"cix":2,"np":2,"it":[{"ty":"sh","bm":0,"hd":false,"mn":"ADBE Vector Shape - Group","nm":"Path 1","ix":1,"d":1,"ks":{"a":0,"k":{"c":true,"i":[[1.183,0],[0.228,0.769],[0,0],[0,0],[-0.978,0.044],[-0.045,-0.978],[0,0],[0,0]],"o":[[-0.764,0],[0,0],[0,0],[-0.044,-0.978],[0.981,-0.035],[0,0],[0,0],[0.338,1.138]],"v":[[8.712,85.472],[7.014,84.204],[-4.604,45.127],[-10.484,-83.619],[-8.794,-85.471],[-6.942,-83.78],[-1.144,44.325],[10.411,83.193]]},"ix":2}},{"ty":"fl","bm":0,"hd":false,"mn":"ADBE Vector Graphic - Fill","nm":"Fill 1","c":{"a":0,"k":[0.1608,0.1725,0.3373],"ix":4},"r":1,"o":{"a":0,"k":100,"ix":5}},{"ty":"tr","a":{"a":0,"k":[0,0],"ix":1},"s":{"a":0,"k":[100,100],"ix":3},"sk":{"a":0,"k":0,"ix":4},"p":{"a":0,"k":[0,0],"ix":2},"r":{"a":0,"k":0,"ix":6},"sa":{"a":0,"k":0,"ix":5},"o":{"a":0,"k":100,"ix":7}}]},{"ty":"tr","a":{"a":0,"k":[0,0],"ix":1},"s":{"a":0,"k":[100,100],"ix":3},"sk":{"a":0,"k":0,"ix":4},"p":{"a":0,"k":[378.099,339.926],"ix":2},"r":{"a":0,"k":0,"ix":6},"sa":{"a":0,"k":0,"ix":5},"o":{"a":0,"k":100,"ix":7}}]},{"ty":"gr","bm":0,"hd":false,"mn":"ADBE Vector Group","nm":"Group 3","ix":3,"cix":2,"np":2,"it":[{"ty":"gr","bm":0,"hd":false,"mn":"ADBE Vector Group","nm":"Group 1","ix":1,"cix":2,"np":3,"it":[{"ty":"sh","bm":0,"hd":false,"mn":"ADBE Vector Shape - Group","nm":"Path 1","ix":1,"d":1,"ks":{"a":0,"k":{"c":true,"i":[[0,0],[0,0],[0,0],[0,0],[0,0],[0,0],[1.501,-0.212]],"o":[[0,0],[0,0],[0,0],[0,0],[0,0],[1.136,0.995],[0,0]],"v":[[-11,2.404],[-0.202,45.939],[11.255,-51.276],[2.882,-53.622],[-9.414,-11.459],[1.089,-2.258],[0.169,0.83]]},"ix":2}},{"ty":"sh","bm":0,"hd":false,"mn":"ADBE Vector Shape - Group","nm":"Path 2","ix":2,"d":1,"ks":{"a":0,"k":{"c":true,"i":[[0.473,1.906],[0,0],[-1.035,0.146],[0,0],[0,0],[-0.193,0.661],[0,0],[-0.939,-0.262],[0,0],[0.102,-0.867],[0,0]],"o":[[0,0],[-0.253,-1.025],[0,0],[0,0],[-0.519,-0.454],[0,0],[0.272,-0.934],[0,0],[0.84,0.235],[0,0],[-0.23,1.95]],"v":[[-1.301,56.235],[-14.913,1.35],[-13.44,-0.832],[-4.156,-2.14],[-12.6,-9.536],[-13.134,-11.366],[-0.031,-56.298],[2.15,-57.509],[13.672,-54.28],[14.954,-52.365],[2.18,56.016]]},"ix":2}},{"ty":"fl","bm":0,"hd":false,"mn":"ADBE Vector Graphic - Fill","nm":"Fill 1","c":{"a":0,"k":[0.1608,0.1725,0.3373],"ix":4},"r":1,"o":{"a":0,"k":100,"ix":5}},{"ty":"tr","a":{"a":0,"k":[0,0],"ix":1},"s":{"a":0,"k":[100,100],"ix":3},"sk":{"a":0,"k":0,"ix":4},"p":{"a":0,"k":[258.833,261.904],"ix":2},"r":{"a":0,"k":0,"ix":6},"sa":{"a":0,"k":0,"ix":5},"o":{"a":0,"k":100,"ix":7}}]},{"ty":"gr","bm":0,"hd":false,"mn":"ADBE Vector Group","nm":"Group 2","ix":2,"cix":2,"np":2,"it":[{"ty":"sh","bm":0,"hd":false,"mn":"ADBE Vector Shape - Group","nm":"Path 1","ix":1,"d":1,"ks":{"a":0,"k":{"c":true,"i":[[3.841,1.076],[4.368,-14.977],[-3.784,-3.315],[4.371,-0.616],[-4.537,-18.295],[-4.258,36.127]],"o":[[-4.368,14.977],[3.784,3.315],[-4.371,0.616],[4.537,18.295],[4.258,-36.127],[-3.841,-1.076]],"v":[[1.671,-55.805],[-11.433,-10.873],[-0.079,-0.928],[-13.193,0.92],[0.419,55.805],[13.193,-52.576]]},"ix":2}},{"ty":"fl","bm":0,"hd":false,"mn":"ADBE Vector Graphic - Fill","nm":"Fill 1","c":{"a":0,"k":[1,1,1],"ix":4},"r":1,"o":{"a":0,"k":100,"ix":5}},{"ty":"tr","a":{"a":0,"k":[0,0],"ix":1},"s":{"a":0,"k":[100,100],"ix":3},"sk":{"a":0,"k":0,"ix":4},"p":{"a":0,"k":[258.834,261.907],"ix":2},"r":{"a":0,"k":0,"ix":6},"sa":{"a":0,"k":0,"ix":5},"o":{"a":0,"k":100,"ix":7}}]},{"ty":"tr","a":{"a":0,"k":[258.834,261.907],"ix":1},"s":{"a":0,"k":[100,100],"ix":3},"sk":{"a":0,"k":0,"ix":4},"p":{"a":0,"k":[258.834,261.907],"ix":2},"r":{"a":0,"k":0,"ix":6},"sa":{"a":0,"k":0,"ix":5},"o":{"a":0,"k":100,"ix":7}}]},{"ty":"gr","bm":0,"hd":false,"mn":"ADBE Vector Group","nm":"Group 4","ix":4,"cix":2,"np":2,"it":[{"ty":"gr","bm":0,"hd":false,"mn":"ADBE Vector Group","nm":"Group 1","ix":1,"cix":2,"np":3,"it":[{"ty":"sh","bm":0,"hd":false,"mn":"ADBE Vector Shape - Group","nm":"Path 1","ix":1,"d":1,"ks":{"a":0,"k":{"c":true,"i":[[0,0],[0,0],[-1.989,28.47],[0,0],[0.02,0.576],[0,0],[0,0],[14.238,1.013],[11.852,-6.996],[4.578,-102.552],[0.317,-1.037]],"o":[[0,0],[28.3,3.686],[0,0],[0.093,-1.341],[0,0],[0,0],[-13.708,-5.305],[-10.892,-0.776],[-15.636,9.226],[-2.107,47.233],[0,0]],"v":[[-110.354,149.983],[-50.759,157.739],[5.022,112.092],[5.666,102.89],[18.697,-3.154],[17.675,-33.14],[31.245,-148.273],[-10.86,-157.793],[-49.449,-151.792],[-76.029,-18.487],[-78.217,44.267]]},"ix":2}},{"ty":"sh","bm":0,"hd":false,"mn":"ADBE Vector Shape - Group","nm":"Path 2","ix":2,"d":1,"ks":{"a":0,"k":{"c":true,"i":[[26.895,-0.002],[65.891,8.575],[-0.315,1.047],[0,0],[-0.923,20.702],[-18.358,10.833],[-11.36,-0.806],[-14.44,-5.736],[0.094,-0.798],[0,0],[0,0],[0,0],[0,0]],"o":[[-5.007,0],[-1.084,-0.142],[0,0],[0.475,-20.509],[4.404,-98.636],[12.706,-7.499],[15.041,1.071],[0.746,0.296],[0,0],[0,0],[0,0],[0,0],[-1.999,28.595]],"v":[[-44.207,161.712],[-112.88,153.23],[-114.349,150.962],[-81.678,43.459],[-79.57,-18.645],[-51.251,-154.845],[-10.609,-161.329],[33.82,-151.071],[34.926,-149.217],[21.211,-32.859],[22.208,-4.196],[8.994,106.111],[8.559,112.34]]},"ix":2}},{"ty":"fl","bm":0,"hd":false,"mn":"ADBE Vector Graphic - Fill","nm":"Fill 1","c":{"a":0,"k":[0.1608,0.1725,0.3373],"ix":4},"r":1,"o":{"a":0,"k":100,"ix":5}},{"ty":"tr","a":{"a":0,"k":[0,0],"ix":1},"s":{"a":0,"k":[100,100],"ix":3},"sk":{"a":0,"k":0,"ix":4},"p":{"a":0,"k":[238.861,358.755],"ix":2},"r":{"a":0,"k":0,"ix":6},"sa":{"a":0,"k":0,"ix":5},"o":{"a":0,"k":100,"ix":7}}]},{"ty":"gr","bm":0,"hd":false,"mn":"ADBE Vector Group","nm":"Group 2","ix":2,"cix":2,"np":2,"it":[{"ty":"sh","bm":0,"hd":false,"mn":"ADBE Vector Shape - Group","nm":"Path 1","ix":1,"d":1,"ks":{"a":0,"k":{"c":true,"i":[[0,0],[0.344,9.905],[-4.577,38.831],[10.543,0.75],[11.78,-6.952],[4.612,-103.312],[0.357,-15.462],[0,0],[-20.555,-2.675],[-2.059,29.454],[0,0]],"o":[[-0.344,-9.905],[4.577,-38.831],[-17.901,-7.11],[-12.637,-0.899],[-16.337,9.641],[-1.137,25.471],[0,0],[20.555,2.675],[29.279,3.81],[0,0],[0,0]],"v":[[20.468,-3.211],[19.435,-32.927],[33.165,-149.42],[-10.735,-159.556],[-50.35,-153.313],[-77.8,-18.561],[-79.912,43.751],[-112.652,151.477],[-50.988,159.502],[6.79,112.221],[7.434,103.019]]},"ix":2}},{"ty":"fl","bm":0,"hd":false,"mn":"ADBE Vector Graphic - Fill","nm":"Fill 1","c":{"a":0,"k":[1,1,1],"ix":4},"r":1,"o":{"a":0,"k":100,"ix":5}},{"ty":"tr","a":{"a":0,"k":[0,0],"ix":1},"s":{"a":0,"k":[100,100],"ix":3},"sk":{"a":0,"k":0,"ix":4},"p":{"a":0,"k":[238.861,358.751],"ix":2},"r":{"a":0,"k":0,"ix":6},"sa":{"a":0,"k":0,"ix":5},"o":{"a":0,"k":100,"ix":7}}]},{"ty":"tr","a":{"a":0,"k":[238.861,358.751],"ix":1},"s":{"a":0,"k":[100,100],"ix":3},"sk":{"a":0,"k":0,"ix":4},"p":{"a":0,"k":[238.861,358.751],"ix":2},"r":{"a":0,"k":0,"ix":6},"sa":{"a":0,"k":0,"ix":5},"o":{"a":0,"k":100,"ix":7}}]},{"ty":"gr","bm":0,"hd":false,"mn":"ADBE Vector Group","nm":"Group 5","ix":5,"cix":2,"np":2,"it":[{"ty":"gr","bm":0,"hd":false,"mn":"ADBE Vector Group","nm":"Group 1","ix":1,"cix":2,"np":3,"it":[{"ty":"sh","bm":0,"hd":false,"mn":"ADBE Vector Shape - Group","nm":"Path 1","ix":1,"d":1,"ks":{"a":0,"k":{"c":true,"i":[[0,0],[0,0],[0,0],[0,0],[-1.343,0.294],[0,0],[0,0]],"o":[[0,0],[0,0],[0,0],[-0.95,-1.002],[0,0],[0,0],[0,0]],"v":[[-3.883,-53.074],[-7.815,45.032],[6.867,8.787],[-2.118,-0.683],[-1.212,-3.634],[8.111,-5.681],[4.623,-51.77]]},"ix":2}},{"ty":"sh","bm":0,"hd":false,"mn":"ADBE Vector Shape - Group","nm":"Path 2","ix":2,"d":1,"ks":{"a":0,"k":{"c":true,"i":[[-0.079,1.977],[0,0],[-1.026,-0.166],[0,0],[-0.062,-0.822],[0,0],[0.863,-0.189],[0,0],[0,0],[0.261,-0.644],[0,0]],"o":[[0,0],[0.042,-1.067],[0,0],[0.815,0.125],[0,0],[0.067,0.881],[0,0],[0,0],[0.478,0.505],[0,0],[-0.743,1.834]],"v":[[-11.765,55.061],[-7.345,-55.198],[-5.306,-56.879],[6.553,-55.06],[8.052,-53.443],[11.761,-4.414],[10.374,-2.549],[2.616,-0.845],[10.224,7.174],[10.581,9.06],[-8.351,55.798]]},"ix":2}},{"ty":"fl","bm":0,"hd":false,"mn":"ADBE Vector Graphic - Fill","nm":"Fill 1","c":{"a":0,"k":[0.1608,0.1725,0.3373],"ix":4},"r":1,"o":{"a":0,"k":100,"ix":5}},{"ty":"tr","a":{"a":0,"k":[0,0],"ix":1},"s":{"a":0,"k":[100,100],"ix":3},"sk":{"a":0,"k":0,"ix":4},"p":{"a":0,"k":[338.004,278.46],"ix":2},"r":{"a":0,"k":0,"ix":6},"sa":{"a":0,"k":0,"ix":5},"o":{"a":0,"k":100,"ix":7}}]},{"ty":"gr","bm":0,"hd":false,"mn":"ADBE Vector Group","nm":"Group 2","ix":2,"cix":2,"np":2,"it":[{"ty":"sh","bm":0,"hd":false,"mn":"ADBE Vector Shape - Group","nm":"Path 1","ix":1,"d":1,"ks":{"a":0,"k":{"c":true,"i":[[0,0],[1.473,-36.753],[-6.311,15.579],[3.256,3.432],[-3.608,0.792],[1.236,16.343]],"o":[[-1.473,36.753],[6.311,-15.579],[-3.256,-3.432],[3.608,-0.792],[-1.236,-16.343],[0,0]],"v":[[-5.574,-55.129],[-9.994,55.129],[8.938,8.392],[-0.832,-1.905],[9.994,-4.282],[6.285,-53.311]]},"ix":2}},{"ty":"fl","bm":0,"hd":false,"mn":"ADBE Vector Graphic - Fill","nm":"Fill 1","c":{"a":0,"k":[1,1,1],"ix":4},"r":1,"o":{"a":0,"k":100,"ix":5}},{"ty":"tr","a":{"a":0,"k":[0,0],"ix":1},"s":{"a":0,"k":[100,100],"ix":3},"sk":{"a":0,"k":0,"ix":4},"p":{"a":0,"k":[338.004,278.462],"ix":2},"r":{"a":0,"k":0,"ix":6},"sa":{"a":0,"k":0,"ix":5},"o":{"a":0,"k":100,"ix":7}}]},{"ty":"tr","a":{"a":0,"k":[338.004,278.462],"ix":1},"s":{"a":0,"k":[100,100],"ix":3},"sk":{"a":0,"k":0,"ix":4},"p":{"a":0,"k":[338.004,278.462],"ix":2},"r":{"a":0,"k":0,"ix":6},"sa":{"a":0,"k":0,"ix":5},"o":{"a":0,"k":100,"ix":7}}]},{"ty":"gr","bm":0,"hd":false,"mn":"ADBE Vector Group","nm":"Group 6","ix":6,"cix":2,"np":1,"it":[{"ty":"gr","bm":0,"hd":false,"mn":"ADBE Vector Group","nm":"Group 1","ix":1,"cix":2,"np":2,"it":[{"ty":"sh","bm":0,"hd":false,"mn":"ADBE Vector Shape - Group","nm":"Path 1","ix":1,"d":1,"ks":{"a":0,"k":{"c":true,"i":[[6.845,8.456],[-12.286,-1.688],[0,0]],"o":[[0,0],[0,0],[0,0]],"v":[[-9.722,-9.16],[8.092,9.16],[9.722,0.835]]},"ix":2}},{"ty":"fl","bm":0,"hd":false,"mn":"ADBE Vector Graphic - Fill","nm":"Fill 1","c":{"a":0,"k":[0.1608,0.1725,0.3373],"ix":4},"r":1,"o":{"a":0,"k":100,"ix":5}},{"ty":"tr","a":{"a":0,"k":[0,0],"ix":1},"s":{"a":0,"k":[100,100],"ix":3},"sk":{"a":0,"k":0,"ix":4},"p":{"a":0,"k":[0,0],"ix":2},"r":{"a":0,"k":0,"ix":6},"sa":{"a":0,"k":0,"ix":5},"o":{"a":0,"k":100,"ix":7}}]},{"ty":"tr","a":{"a":0,"k":[0,0],"ix":1},"s":{"a":0,"k":[100,100],"ix":3},"sk":{"a":0,"k":0,"ix":4},"p":{"a":0,"k":[302.842,199.968],"ix":2},"r":{"a":0,"k":0,"ix":6},"sa":{"a":0,"k":0,"ix":5},"o":{"a":0,"k":100,"ix":7}}]},{"ty":"gr","bm":0,"hd":false,"mn":"ADBE Vector Group","nm":"Group 7","ix":7,"cix":2,"np":2,"it":[{"ty":"gr","bm":0,"hd":false,"mn":"ADBE Vector Group","nm":"Group 1","ix":1,"cix":2,"np":2,"it":[{"ty":"sh","bm":0,"hd":false,"mn":"ADBE Vector Shape - Group","nm":"Path 1","ix":1,"d":1,"ks":{"a":0,"k":{"c":true,"i":[[0.723,1.35],[0,0],[-2.258,11.533],[-0.962,-0.189],[0.188,-0.961],[0,0],[0,0],[-2.563,11.344],[-0.957,-0.215],[0.215,-0.956],[12.397,-34.329]],"o":[[0,0],[-0.415,-0.773],[0.188,-0.962],[0.961,0.188],[0,0],[0,0],[10.489,-29.048],[0.216,-0.956],[0.955,0.216],[-2.626,11.621],[-0.519,1.441]],"v":[[1.723,23.795],[-17.109,-11.35],[-15.178,-23.297],[-13.098,-24.696],[-11.698,-22.616],[-13.686,-12.467],[2.969,18.616],[13.8,-14.563],[15.92,-15.901],[17.258,-13.781],[4.952,23.561]]},"ix":2}},{"ty":"fl","bm":0,"hd":false,"mn":"ADBE Vector Graphic - Fill","nm":"Fill 1","c":{"a":0,"k":[0.1608,0.1725,0.3373],"ix":4},"r":1,"o":{"a":0,"k":100,"ix":5}},{"ty":"tr","a":{"a":0,"k":[0,0],"ix":1},"s":{"a":0,"k":[100,100],"ix":3},"sk":{"a":0,"k":0,"ix":4},"p":{"a":0,"k":[295.405,223.3],"ix":2},"r":{"a":0,"k":0,"ix":6},"sa":{"a":0,"k":0,"ix":5},"o":{"a":0,"k":100,"ix":7}}]},{"ty":"gr","bm":0,"hd":false,"mn":"ADBE Vector Group","nm":"Group 2","ix":2,"cix":2,"np":2,"it":[{"ty":"sh","bm":0,"hd":false,"mn":"ADBE Vector Shape - Group","nm":"Path 1","ix":1,"d":1,"ks":{"a":0,"k":{"c":true,"i":[[0,0],[0,0],[0,0],[-2.451,10.848]],"o":[[0,0],[0,0],[11.859,-32.84],[0,0]],"v":[[-13.43,-22.958],[-15.538,-12.188],[3.293,22.958],[15.538,-14.173]]},"ix":2}},{"ty":"fl","bm":0,"hd":false,"mn":"ADBE Vector Graphic - Fill","nm":"Fill 1","c":{"a":0,"k":[1,1,1],"ix":4},"r":1,"o":{"a":0,"k":100,"ix":5}},{"ty":"tr","a":{"a":0,"k":[0,0],"ix":1},"s":{"a":0,"k":[100,100],"ix":3},"sk":{"a":0,"k":0,"ix":4},"p":{"a":0,"k":[295.396,223.301],"ix":2},"r":{"a":0,"k":0,"ix":6},"sa":{"a":0,"k":0,"ix":5},"o":{"a":0,"k":100,"ix":7}}]},{"ty":"tr","a":{"a":0,"k":[295.396,223.301],"ix":1},"s":{"a":0,"k":[100,100],"ix":3},"sk":{"a":0,"k":0,"ix":4},"p":{"a":0,"k":[295.396,223.301],"ix":2},"r":{"a":0,"k":0,"ix":6},"sa":{"a":0,"k":0,"ix":5},"o":{"a":0,"k":100,"ix":7}}]},{"ty":"gr","bm":0,"hd":false,"mn":"ADBE Vector Group","nm":"Group 8","ix":8,"cix":2,"np":2,"it":[{"ty":"gr","bm":0,"hd":false,"mn":"ADBE Vector Group","nm":"Group 1","ix":1,"cix":2,"np":3,"it":[{"ty":"sh","bm":0,"hd":false,"mn":"ADBE Vector Shape - Group","nm":"Path 1","ix":1,"d":1,"ks":{"a":0,"k":{"c":true,"i":[[0,0],[0,0],[-26.63,8.588],[0,0],[0,0],[0.085,0.685],[2.402,4.37],[21.584,2.519]],"o":[[0,0],[5.551,27.425],[0,0],[0,0],[-0.314,-0.682],[-2.786,-22.507],[-7.704,-14.016],[0,0]],"v":[[-74.895,26.257],[-58.816,105.707],[1.582,141.065],[28.076,132.524],[-4.007,97.198],[-28.959,16.382],[-35.757,-121.44],[-68.105,-143.145]]},"ix":2}},{"ty":"sh","bm":0,"hd":false,"mn":"ADBE Vector Shape - Group","nm":"Path 2","ix":2,"d":1,"ks":{"a":0,"k":{"c":true,"i":[[5.996,29.626],[0,0],[0,0],[-1.015,-0.1],[-4.409,-6.47],[-12.536,-101.377],[0,0],[0,0],[1.012,-0.327],[0,0]],"o":[[0,0],[0,0],[0.04,-1.02],[23.499,2.367],[9.357,13.73],[0,0],[0,0],[0.445,0.966],[0,0],[-28.508,9.192]],"v":[[-62.29,106.41],[-78.446,26.328],[-71.571,-145.183],[-69.623,-146.876],[-32.946,-123.6],[-25.58,14.822],[-0.263,96.851],[32.133,132.855],[31.067,135.284],[2.669,144.439]]},"ix":2}},{"ty":"fl","bm":0,"hd":false,"mn":"ADBE Vector Graphic - Fill","nm":"Fill 1","c":{"a":0,"k":[0.1608,0.1725,0.3373],"ix":4},"r":1,"o":{"a":0,"k":100,"ix":5}},{"ty":"tr","a":{"a":0,"k":[0,0],"ix":1},"s":{"a":0,"k":[100,100],"ix":3},"sk":{"a":0,"k":0,"ix":4},"p":{"a":0,"k":[402.23,368.445],"ix":2},"r":{"a":0,"k":0,"ix":6},"sa":{"a":0,"k":0,"ix":5},"o":{"a":0,"k":100,"ix":7}}]},{"ty":"gr","bm":0,"hd":false,"mn":"ADBE Vector Group","nm":"Group 2","ix":2,"cix":2,"np":2,"it":[{"ty":"sh","bm":0,"hd":false,"mn":"ADBE Vector Shape - Group","nm":"Path 1","ix":1,"d":1,"ks":{"a":0,"k":{"c":true,"i":[[4.47,32.891],[10.371,13.825],[14.158,1.426],[2.292,-57.171],[-5.374,-26.553],[-27.656,8.915],[0,0],[6.557,14.214]],"o":[[-12.569,-101.551],[-13.569,-18.088],[-2.292,57.17],[5.374,26.553],[5.764,28.48],[0,0],[-6.557,-14.214],[-1.583,-20.901]],"v":[[-27.2,16.16],[-34.351,-122.524],[-69.8,-145.116],[-76.674,26.395],[-60.553,106.054],[2.126,142.748],[30.524,133.593],[-2.397,96.452]]},"ix":2}},{"ty":"fl","bm":0,"hd":false,"mn":"ADBE Vector Graphic - Fill","nm":"Fill 1","c":{"a":0,"k":[1,1,1],"ix":4},"r":1,"o":{"a":0,"k":100,"ix":5}},{"ty":"tr","a":{"a":0,"k":[0,0],"ix":1},"s":{"a":0,"k":[100,100],"ix":3},"sk":{"a":0,"k":0,"ix":4},"p":{"a":0,"k":[402.229,368.449],"ix":2},"r":{"a":0,"k":0,"ix":6},"sa":{"a":0,"k":0,"ix":5},"o":{"a":0,"k":100,"ix":7}}]},{"ty":"tr","a":{"a":0,"k":[402.229,368.449],"ix":1},"s":{"a":0,"k":[100,100],"ix":3},"sk":{"a":0,"k":0,"ix":4},"p":{"a":0,"k":[402.229,368.449],"ix":2},"r":{"a":0,"k":0,"ix":6},"sa":{"a":0,"k":0,"ix":5},"o":{"a":0,"k":100,"ix":7}}]},{"ty":"gr","bm":0,"hd":false,"mn":"ADBE Vector Group","nm":"Group 9","ix":9,"cix":2,"np":1,"it":[{"ty":"gr","bm":0,"hd":false,"mn":"ADBE Vector Group","nm":"Group 1","ix":1,"cix":2,"np":2,"it":[{"ty":"sh","bm":0,"hd":false,"mn":"ADBE Vector Shape - Group","nm":"Path 1","ix":1,"d":1,"ks":{"a":0,"k":{"c":true,"i":[[0,0],[20.525,-27.249],[0,0],[0,0],[3.185,22.844]],"o":[[0,0],[-20.525,27.249],[0,0],[0,0],[-3.185,-22.844]],"v":[[14.728,-83.478],[-89.159,-83.478],[-75.711,95.588],[58.765,95.588],[80.069,-50.81]]},"ix":2}},{"ty":"fl","bm":0,"hd":false,"mn":"ADBE Vector Graphic - Fill","nm":"Fill 1","c":{"a":0,"k":[0,0.4,1],"ix":4},"r":1,"o":{"a":0,"k":100,"ix":5}},{"ty":"tr","a":{"a":0,"k":[0,0],"ix":1},"s":{"a":0,"k":[100,100],"ix":3},"sk":{"a":0,"k":0,"ix":4},"p":{"a":0,"k":[0,0],"ix":2},"r":{"a":0,"k":0,"ix":6},"sa":{"a":0,"k":0,"ix":5},"o":{"a":0,"k":100,"ix":7}}]},{"ty":"tr","a":{"a":0,"k":[0,0],"ix":1},"s":{"a":0,"k":[100,100],"ix":3},"sk":{"a":0,"k":0,"ix":4},"p":{"a":0,"k":[284.526,299.943],"ix":2},"r":{"a":0,"k":0,"ix":6},"sa":{"a":0,"k":0,"ix":5},"o":{"a":0,"k":100,"ix":7}}]},{"ty":"gr","bm":0,"hd":false,"mn":"ADBE Vector Group","nm":"Group 10","ix":10,"cix":2,"np":2,"it":[{"ty":"gr","bm":0,"hd":false,"mn":"ADBE Vector Group","nm":"Group 1","ix":1,"cix":2,"np":3,"it":[{"ty":"sh","bm":0,"hd":false,"mn":"ADBE Vector Shape - Group","nm":"Path 1","ix":1,"d":1,"ks":{"a":0,"k":{"c":true,"i":[[0,0],[0,0],[0,0],[0,0]],"o":[[0,0],[0,0],[0,0],[0,0]],"v":[[-18.103,23.33],[7.972,28.434],[18.103,-23.329],[-7.972,-28.433]]},"ix":2}},{"ty":"sh","bm":0,"hd":false,"mn":"ADBE Vector Shape - Group","nm":"Path 2","ix":2,"d":1,"ks":{"a":0,"k":{"c":true,"i":[[0.831,0],[0,0],[-0.187,0.96],[0,0],[-0.968,-0.19],[0,0],[0.187,-0.96],[0,0]],"o":[[0,0],[-0.96,-0.187],[0,0],[0.187,-0.962],[0,0],[0.96,0.187],[0,0],[-0.165,0.846]],"v":[[9.373,32.286],[-20.523,26.469],[-21.923,24.39],[-11.111,-30.853],[-9.031,-32.252],[20.523,-26.468],[21.923,-24.388],[11.111,30.854]]},"ix":2}},{"ty":"fl","bm":0,"hd":false,"mn":"ADBE Vector Graphic - Fill","nm":"Fill 1","c":{"a":0,"k":[0.1608,0.1725,0.3373],"ix":4},"r":1,"o":{"a":0,"k":100,"ix":5}},{"ty":"tr","a":{"a":0,"k":[0,0],"ix":1},"s":{"a":0,"k":[100,100],"ix":3},"sk":{"a":0,"k":0,"ix":4},"p":{"a":0,"k":[297.31,200.343],"ix":2},"r":{"a":0,"k":0,"ix":6},"sa":{"a":0,"k":0,"ix":5},"o":{"a":0,"k":100,"ix":7}}]},{"ty":"gr","bm":0,"hd":false,"mn":"ADBE Vector Group","nm":"Group 2","ix":2,"cix":2,"np":2,"it":[{"ty":"sh","bm":0,"hd":false,"mn":"ADBE Vector Shape - Group","nm":"Path 1","ix":1,"d":1,"ks":{"a":0,"k":{"c":true,"i":[[0,0],[0,0],[0,0],[0,0]],"o":[[0,0],[0,0],[0,0],[0,0]],"v":[[9.371,30.513],[-20.183,24.729],[-9.371,-30.513],[20.183,-24.729]]},"ix":2}},{"ty":"fl","bm":0,"hd":false,"mn":"ADBE Vector Graphic - Fill","nm":"Fill 1","c":{"a":0,"k":[1,1,1],"ix":4},"r":1,"o":{"a":0,"k":100,"ix":5}},{"ty":"tr","a":{"a":0,"k":[0,0],"ix":1},"s":{"a":0,"k":[100,100],"ix":3},"sk":{"a":0,"k":0,"ix":4},"p":{"a":0,"k":[297.31,200.344],"ix":2},"r":{"a":0,"k":0,"ix":6},"sa":{"a":0,"k":0,"ix":5},"o":{"a":0,"k":100,"ix":7}}]},{"ty":"tr","a":{"a":0,"k":[297.31,200.344],"ix":1},"s":{"a":0,"k":[100,100],"ix":3},"sk":{"a":0,"k":0,"ix":4},"p":{"a":0,"k":[297.31,200.344],"ix":2},"r":{"a":0,"k":0,"ix":6},"sa":{"a":0,"k":0,"ix":5},"o":{"a":0,"k":100,"ix":7}}]}],"ind":4},{"ty":4,"nm":"legs","sr":1,"st":0,"op":180,"ip":0,"hd":false,"ddd":0,"bm":0,"hasMask":false,"ao":0,"ks":{"a":{"a":0,"k":[301.528,638.034,0],"ix":1},"s":{"a":0,"k":[100,100,100],"ix":6},"sk":{"a":0,"k":0},"p":{"a":0,"k":[828.6103196939848,622.034],"ix":2},"r":{"a":0,"k":0,"ix":10},"sa":{"a":0,"k":0},"o":{"a":0,"k":100,"ix":11}},"shapes":[{"ty":"gr","bm":0,"hd":false,"mn":"ADBE Vector Group","nm":"Group 1","ix":1,"cix":2,"np":1,"it":[{"ty":"gr","bm":0,"hd":false,"mn":"ADBE Vector Group","nm":"Group 1","ix":1,"cix":2,"np":2,"it":[{"ty":"sh","bm":0,"hd":false,"mn":"ADBE Vector Shape - Group","nm":"Path 1","ix":1,"d":1,"ks":{"a":1,"k":[{"o":{"x":0.333,"y":0},"i":{"x":0.667,"y":1},"s":[{"c":true,"i":[[0,0],[7.435,-23.768],[-0.61,-46.12],[-0.573,-21.703],[15.05,-91.252],[-47.593,0],[-4.369,30.002],[-1.757,57.736],[2.625,99.418],[-0.028,-1.339]],"o":[[-8.998,10.764],[-5.827,18.628],[0.414,31.266],[-15.05,91.252],[47.593,0],[6.732,-57.87],[0,0],[0.949,-31.173],[-1.087,-41.145],[0,0]],"v":[[-20.605,-255.503],[-49.348,-203.579],[-54.892,-124.293],[-59.308,-37.23],[-86.458,242.526],[56.321,242.526],[68.547,110.24],[68.258,-28.71],[69.996,-157.977],[67.89,-255.503]]}],"t":0},{"o":{"x":0.333,"y":0},"i":{"x":0.833,"y":1},"s":[{"c":true,"i":[[0,0],[7.435,-23.768],[-0.61,-46.12],[-0.573,-21.703],[15.05,-91.252],[-47.593,0],[-4.369,30.002],[-1.757,57.736],[2.625,99.418],[-0.028,-1.339]],"o":[[-8.998,10.764],[-5.827,18.628],[0.414,31.266],[-15.05,91.252],[47.593,0],[6.732,-57.87],[0,0],[0.949,-31.173],[-1.087,-41.145],[0,0]],"v":[[-8.605,-242.503],[-37.348,-190.579],[-42.892,-111.293],[-41.308,-31.23],[-86.458,242.526],[56.321,242.526],[73.547,110.24],[86.258,-22.71],[81.996,-144.977],[79.89,-242.503]]}],"t":20},{"o":{"x":0.167,"y":0},"i":{"x":0.833,"y":1},"s":[{"c":true,"i":[[0,0],[7.435,-23.768],[-0.61,-46.12],[-0.573,-21.703],[15.05,-91.252],[-47.593,0],[-4.369,30.002],[-1.757,57.736],[2.625,99.418],[-0.028,-1.339]],"o":[[-8.998,10.764],[-5.827,18.628],[0.414,31.266],[-15.05,91.252],[47.593,0],[6.732,-57.87],[0,0],[0.949,-31.173],[-1.087,-41.145],[0,0]],"v":[[-8.605,-242.503],[-37.348,-190.579],[-42.892,-111.293],[-41.308,-31.23],[-86.458,242.526],[56.321,242.526],[73.547,110.24],[86.258,-22.71],[81.996,-144.977],[79.89,-242.503]]}],"t":30},{"o":{"x":0.167,"y":0},"i":{"x":0.833,"y":1},"s":[{"c":true,"i":[[0,0],[7.435,-23.768],[-0.61,-46.12],[-0.573,-21.703],[15.05,-91.252],[-47.593,0],[-4.369,30.002],[-1.757,57.736],[2.625,99.418],[-0.028,-1.339]],"o":[[-8.998,10.764],[-5.827,18.628],[0.414,31.266],[-15.05,91.252],[47.593,0],[6.732,-57.87],[0,0],[0.949,-31.173],[-1.087,-41.145],[0,0]],"v":[[-15.605,-242.503],[-44.348,-190.579],[-49.892,-111.293],[-48.308,-31.23],[-86.458,242.526],[56.321,242.526],[73.547,110.24],[79.258,-22.71],[74.996,-144.977],[72.89,-242.503]]}],"t":53},{"o":{"x":0.167,"y":0},"i":{"x":0.833,"y":1},"s":[{"c":true,"i":[[0,0],[7.435,-23.768],[-0.61,-46.12],[-0.573,-21.703],[15.05,-91.252],[-47.593,0],[-4.369,30.002],[-1.757,57.736],[2.625,99.418],[-0.028,-1.339]],"o":[[-8.998,10.764],[-5.827,18.628],[0.414,31.266],[-15.05,91.252],[47.593,0],[6.732,-57.87],[0,0],[0.949,-31.173],[-1.087,-41.145],[0,0]],"v":[[-8.605,-242.503],[-37.348,-190.579],[-42.892,-111.293],[-41.308,-31.23],[-86.458,242.526],[56.321,242.526],[73.547,110.24],[86.258,-22.71],[81.996,-144.977],[79.89,-242.503]]}],"t":77},{"o":{"x":0.167,"y":0},"i":{"x":0.667,"y":1},"s":[{"c":true,"i":[[0,0],[7.435,-23.768],[-0.61,-46.12],[-0.573,-21.703],[15.05,-91.252],[-47.593,0],[-4.369,30.002],[-1.757,57.736],[2.625,99.418],[-0.028,-1.339]],"o":[[-8.998,10.764],[-5.827,18.628],[0.414,31.266],[-15.05,91.252],[47.593,0],[6.732,-57.87],[0,0],[0.949,-31.173],[-1.087,-41.145],[0,0]],"v":[[-8.605,-242.503],[-37.348,-190.579],[-42.892,-111.293],[-41.308,-31.23],[-86.458,242.526],[56.321,242.526],[73.547,110.24],[86.258,-22.71],[81.996,-144.977],[79.89,-242.503]]}],"t":90},{"s":[{"c":true,"i":[[0,0],[7.435,-23.768],[-0.61,-46.12],[-0.573,-21.703],[15.05,-91.252],[-47.593,0],[-4.369,30.002],[-1.757,57.736],[2.625,99.418],[-0.028,-1.339]],"o":[[-8.998,10.764],[-5.827,18.628],[0.414,31.266],[-15.05,91.252],[47.593,0],[6.732,-57.87],[0,0],[0.949,-31.173],[-1.087,-41.145],[0,0]],"v":[[-20.605,-255.503],[-49.348,-203.579],[-54.892,-124.293],[-59.308,-37.23],[-86.458,242.526],[56.321,242.526],[68.547,110.24],[68.258,-28.71],[69.996,-157.977],[67.89,-255.503]]}],"t":110}],"ix":2}},{"ty":"fl","bm":0,"hd":false,"mn":"ADBE Vector Graphic - Fill","nm":"Fill 1","c":{"a":0,"k":[0,0.4,1],"ix":4},"r":1,"o":{"a":0,"k":100,"ix":5}},{"ty":"tr","a":{"a":0,"k":[0,0],"ix":1},"s":{"a":0,"k":[100,100],"ix":3},"sk":{"a":0,"k":0,"ix":4},"p":{"a":0,"k":[0,0],"ix":2},"r":{"a":0,"k":0,"ix":6},"sa":{"a":0,"k":0,"ix":5},"o":{"a":0,"k":100,"ix":7}}]},{"ty":"tr","a":{"a":0,"k":[0,0],"ix":1},"s":{"a":0,"k":[100,100],"ix":3},"sk":{"a":0,"k":0,"ix":4},"p":{"a":0,"k":[217.42,638.034],"ix":2},"r":{"a":0,"k":0,"ix":6},"sa":{"a":0,"k":0,"ix":5},"o":{"a":0,"k":100,"ix":7}}]},{"ty":"gr","bm":0,"hd":false,"mn":"ADBE Vector Group","nm":"Group 2","ix":2,"cix":2,"np":1,"it":[{"ty":"gr","bm":0,"hd":false,"mn":"ADBE Vector Group","nm":"Group 1","ix":1,"cix":2,"np":2,"it":[{"ty":"sh","bm":0,"hd":false,"mn":"ADBE Vector Shape - Group","nm":"Path 1","ix":1,"d":1,"ks":{"a":1,"k":[{"o":{"x":0.333,"y":0},"i":{"x":0.667,"y":1},"s":[{"c":true,"i":[[0,0],[-9.608,-41.456],[0,0],[45.854,0],[3.432,89.956],[0,0],[0,0]],"o":[[0,0],[9.608,41.457],[-45.854,0],[-3.432,-89.957],[0,0],[0,0],[0,0]],"v":[[-32.021,-255.514],[72.198,-37.501],[108.782,242.514],[-28.78,242.514],[-57.077,-33.355],[-115.502,-179.235],[-120.782,-255.514]]}],"t":0},{"o":{"x":0.333,"y":0},"i":{"x":0.833,"y":1},"s":[{"c":true,"i":[[0,0],[-9.608,-41.456],[0,0],[45.854,0],[3.432,89.956],[0,0],[0,0]],"o":[[0,0],[9.608,41.457],[-45.854,0],[-3.432,-89.957],[0,0],[0,0],[0,0]],"v":[[-20.021,-242.514],[90.198,-31.501],[108.782,242.514],[-28.78,242.514],[-39.077,-27.355],[-103.502,-166.235],[-108.782,-242.514]]}],"t":20},{"o":{"x":0.167,"y":0},"i":{"x":0.833,"y":1},"s":[{"c":true,"i":[[0,0],[-9.608,-41.456],[0,0],[45.854,0],[3.432,89.956],[0,0],[0,0]],"o":[[0,0],[9.608,41.457],[-45.854,0],[-3.432,-89.957],[0,0],[0,0],[0,0]],"v":[[-20.021,-242.514],[90.198,-31.501],[108.782,242.514],[-28.78,242.514],[-39.077,-27.355],[-103.502,-166.235],[-108.782,-242.514]]}],"t":30},{"o":{"x":0.167,"y":0},"i":{"x":0.833,"y":1},"s":[{"c":true,"i":[[0,0],[-9.608,-41.456],[0,0],[45.854,0],[3.432,89.956],[0,0],[0,0]],"o":[[0,0],[9.608,41.457],[-45.854,0],[-3.432,-89.957],[0,0],[0,0],[0,0]],"v":[[-27.021,-242.514],[83.198,-31.501],[108.782,242.514],[-28.78,242.514],[-46.077,-27.355],[-110.502,-166.235],[-115.782,-242.514]]}],"t":53},{"o":{"x":0.167,"y":0},"i":{"x":0.833,"y":1},"s":[{"c":true,"i":[[0,0],[-9.608,-41.456],[0,0],[45.854,0],[3.432,89.957],[0,0],[0,0]],"o":[[0,0],[9.608,41.457],[-45.854,0],[-3.432,-89.957],[0,0],[0,0],[0,0]],"v":[[-20.021,-242.514],[90.198,-31.501],[108.782,242.514],[-28.78,242.514],[-39.077,-27.355],[-103.502,-166.235],[-108.782,-242.514]]}],"t":77},{"o":{"x":0.167,"y":0},"i":{"x":0.667,"y":1},"s":[{"c":true,"i":[[0,0],[-9.608,-41.456],[0,0],[45.854,0],[3.432,89.957],[0,0],[0,0]],"o":[[0,0],[9.608,41.457],[-45.854,0],[-3.432,-89.957],[0,0],[0,0],[0,0]],"v":[[-20.021,-242.514],[90.198,-31.501],[108.782,242.514],[-28.78,242.514],[-39.077,-27.355],[-103.502,-166.235],[-108.782,-242.514]]}],"t":90},{"s":[{"c":true,"i":[[0,0],[-9.608,-41.456],[0,0],[45.854,0],[3.432,89.957],[0,0],[0,0]],"o":[[0,0],[9.608,41.457],[-45.854,0],[-3.432,-89.957],[0,0],[0,0],[0,0]],"v":[[-32.021,-255.514],[72.198,-37.501],[108.782,242.514],[-28.78,242.514],[-57.077,-33.355],[-115.502,-179.235],[-120.782,-255.514]]}],"t":110}],"ix":2}},{"ty":"fl","bm":0,"hd":false,"mn":"ADBE Vector Graphic - Fill","nm":"Fill 1","c":{"a":0,"k":[0,0.4,1],"ix":4},"r":1,"o":{"a":0,"k":100,"ix":5}},{"ty":"tr","a":{"a":0,"k":[0,0],"ix":1},"s":{"a":0,"k":[100,100],"ix":3},"sk":{"a":0,"k":0,"ix":4},"p":{"a":0,"k":[0,0],"ix":2},"r":{"a":0,"k":0,"ix":6},"sa":{"a":0,"k":0,"ix":5},"o":{"a":0,"k":100,"ix":7}}]},{"ty":"tr","a":{"a":0,"k":[0,0],"ix":1},"s":{"a":0,"k":[100,100],"ix":3},"sk":{"a":0,"k":0,"ix":4},"p":{"a":0,"k":[363.312,638.045],"ix":2},"r":{"a":0,"k":0,"ix":6},"sa":{"a":0,"k":0,"ix":5},"o":{"a":0,"k":100,"ix":7}}]}],"ind":5},{"ty":4,"nm":"shoe","sr":1,"st":0,"op":180,"ip":0,"hd":false,"ddd":0,"bm":0,"hasMask":false,"ao":0,"ks":{"a":{"a":0,"k":[339.642,908.04,0],"ix":1},"s":{"a":0,"k":[100,100,100],"ix":6},"sk":{"a":0,"k":0},"p":{"a":0,"k":[866.7243196939849,892.04],"ix":2},"r":{"a":0,"k":0,"ix":10},"sa":{"a":0,"k":0},"o":{"a":0,"k":100,"ix":11}},"shapes":[{"ty":"gr","bm":0,"hd":false,"mn":"ADBE Vector Group","nm":"Group 1","ix":1,"cix":2,"np":1,"it":[{"ty":"gr","bm":0,"hd":false,"mn":"ADBE Vector Group","nm":"Group 1","ix":1,"cix":2,"np":2,"it":[{"ty":"sh","bm":0,"hd":false,"mn":"ADBE Vector Shape - Group","nm":"Path 1","ix":1,"d":1,"ks":{"a":0,"k":{"c":true,"i":[[27.061,-0.524],[4.642,-37.827],[-68.825,0.038],[15.868,10.986],[17.819,14.431],[2.366,32.052]],"o":[[-4.642,37.827],[68.825,-0.038],[-4.605,-10.266],[-22.951,-15.89],[-9.305,-7.536],[-27.061,0.524]],"v":[[-89.311,-55.955],[-103.237,57.526],[103.237,57.412],[74.214,21.135],[14.579,-3.202],[-8.128,-57.526]]},"ix":2}},{"ty":"fl","bm":0,"hd":false,"mn":"ADBE Vector Graphic - Fill","nm":"Fill 1","c":{"a":0,"k":[0,0.2353,0.5922],"ix":4},"r":1,"o":{"a":0,"k":100,"ix":5}},{"ty":"tr","a":{"a":0,"k":[0,0],"ix":1},"s":{"a":0,"k":[100,100],"ix":3},"sk":{"a":0,"k":0,"ix":4},"p":{"a":0,"k":[0,0],"ix":2},"r":{"a":0,"k":0,"ix":6},"sa":{"a":0,"k":0,"ix":5},"o":{"a":0,"k":100,"ix":7}}]},{"ty":"tr","a":{"a":0,"k":[0,0],"ix":1},"s":{"a":0,"k":[100,100],"ix":3},"sk":{"a":0,"k":0,"ix":4},"p":{"a":0,"k":[235.641,908.04],"ix":2},"r":{"a":0,"k":0,"ix":6},"sa":{"a":0,"k":0,"ix":5},"o":{"a":0,"k":100,"ix":7}}]},{"ty":"gr","bm":0,"hd":false,"mn":"ADBE Vector Group","nm":"Group 2","ix":2,"cix":2,"np":1,"it":[{"ty":"gr","bm":0,"hd":false,"mn":"ADBE Vector Group","nm":"Group 1","ix":1,"cix":2,"np":2,"it":[{"ty":"sh","bm":0,"hd":false,"mn":"ADBE Vector Shape - Group","nm":"Path 1","ix":1,"d":1,"ks":{"a":0,"k":{"c":true,"i":[[27.061,-0.524],[2.706,-37.789],[0,0],[15.868,10.986],[17.819,14.431],[2.366,32.052]],"o":[[-2.706,37.789],[0,0],[-4.605,-10.266],[-22.951,-15.89],[-9.305,-7.536],[-27.061,0.524]],"v":[[-92.215,-55.898],[-100.333,57.469],[100.333,57.469],[71.31,21.192],[11.674,-3.145],[-11.033,-57.469]]},"ix":2}},{"ty":"fl","bm":0,"hd":false,"mn":"ADBE Vector Graphic - Fill","nm":"Fill 1","c":{"a":0,"k":[0,0.2353,0.5922],"ix":4},"r":1,"o":{"a":0,"k":100,"ix":5}},{"ty":"tr","a":{"a":0,"k":[0,0],"ix":1},"s":{"a":0,"k":[100,100],"ix":3},"sk":{"a":0,"k":0,"ix":4},"p":{"a":0,"k":[0,0],"ix":2},"r":{"a":0,"k":0,"ix":6},"sa":{"a":0,"k":0,"ix":5},"o":{"a":0,"k":100,"ix":7}}]},{"ty":"tr","a":{"a":0,"k":[0,0],"ix":1},"s":{"a":0,"k":[100,100],"ix":3},"sk":{"a":0,"k":0,"ix":4},"p":{"a":0,"k":[446.547,907.983],"ix":2},"r":{"a":0,"k":0,"ix":6},"sa":{"a":0,"k":0,"ix":5},"o":{"a":0,"k":100,"ix":7}}]}],"ind":6},{"ty":4,"nm":"l hand","sr":1,"st":0,"op":180,"ip":0,"hd":false,"ddd":0,"bm":0,"hasMask":false,"ao":0,"ks":{"a":{"a":0,"k":[332.73,223.445,0],"ix":1},"s":{"a":0,"k":[100,100,100],"ix":6},"sk":{"a":0,"k":0},"p":{"a":0,"k":[332.73,223.445,0],"ix":2},"r":{"a":1,"k":[{"o":{"x":0.333,"y":0},"i":{"x":0.667,"y":1},"s":[-11],"t":0},{"o":{"x":0.333,"y":0},"i":{"x":0.667,"y":1},"s":[9],"t":20},{"o":{"x":0.333,"y":0},"i":{"x":0.833,"y":1},"s":[9],"t":30},{"o":{"x":0.167,"y":0},"i":{"x":0.667,"y":1},"s":[17],"t":53},{"o":{"x":0.333,"y":0},"i":{"x":0.833,"y":1},"s":[4],"t":77},{"o":{"x":0.167,"y":0},"i":{"x":0.667,"y":1},"s":[4],"t":90},{"s":[-11],"t":110}],"ix":10},"sa":{"a":0,"k":0},"o":{"a":0,"k":100,"ix":11}},"shapes":[{"ty":"gr","bm":0,"hd":false,"mn":"ADBE Vector Group","nm":"Group 1","ix":1,"cix":2,"np":1,"it":[{"ty":"gr","bm":0,"hd":false,"mn":"ADBE Vector Group","nm":"Group 1","ix":1,"cix":2,"np":2,"it":[{"ty":"sh","bm":0,"hd":false,"mn":"ADBE Vector Shape - Group","nm":"Path 1","ix":1,"d":1,"ks":{"a":0,"k":{"c":true,"i":[[0.394,0],[-1.291,1.053],[-0.503,0.089],[-0.171,-0.963],[0.963,-0.173],[9.535,-7.778]],"o":[[-1.66,0],[10.272,-8.38],[0.971,-0.171],[0.172,0.963],[-0.114,0.021],[-0.33,0.268]],"v":[[-10.956,6.921],[-12.077,3.775],[10.648,-6.894],[12.702,-5.46],[11.27,-3.404],[-9.836,6.522]]},"ix":2}},{"ty":"fl","bm":0,"hd":false,"mn":"ADBE Vector Graphic - Fill","nm":"Fill 1","c":{"a":0,"k":[0.1608,0.1725,0.3373],"ix":4},"r":1,"o":{"a":0,"k":100,"ix":5}},{"ty":"tr","a":{"a":0,"k":[0,0],"ix":1},"s":{"a":0,"k":[100,100],"ix":3},"sk":{"a":0,"k":0,"ix":4},"p":{"a":0,"k":[0,0],"ix":2},"r":{"a":0,"k":0,"ix":6},"sa":{"a":0,"k":0,"ix":5},"o":{"a":0,"k":100,"ix":7}}]},{"ty":"tr","a":{"a":0,"k":[0,0],"ix":1},"s":{"a":0,"k":[100,100],"ix":3},"sk":{"a":0,"k":0,"ix":4},"p":{"a":0,"k":[394.071,376.758],"ix":2},"r":{"a":0,"k":0,"ix":6},"sa":{"a":0,"k":0,"ix":5},"o":{"a":0,"k":100,"ix":7}}]},{"ty":"gr","bm":0,"hd":false,"mn":"ADBE Vector Group","nm":"Group 2","ix":2,"cix":2,"np":2,"it":[{"ty":"gr","bm":0,"hd":false,"mn":"ADBE Vector Group","nm":"Group 1","ix":1,"cix":2,"np":3,"it":[{"ty":"sh","bm":0,"hd":false,"mn":"ADBE Vector Shape - Group","nm":"Path 1","ix":1,"d":1,"ks":{"a":0,"k":{"c":true,"i":[[0,0],[0,0],[-0.538,0.524],[0,0],[0,0],[0.085,0.685],[2.472,21.127],[8.356,10.875],[21.584,2.519]],"o":[[0,0],[-0.314,-0.682],[0,0],[0,0],[-0.658,-0.21],[-2.786,-22.507],[-4.053,-34.627],[-9.745,-12.682],[0,0]],"v":[[-74.145,23.132],[9.243,83.198],[13.491,84.936],[73.324,27.626],[2.258,4.852],[1.041,3.382],[-6.882,-62.374],[-20.257,-119.94],[-68.105,-143.145]]},"ix":2}},{"ty":"sh","bm":0,"hd":false,"mn":"ADBE Vector Shape - Group","nm":"Path 2","ix":2,"d":1,"ks":{"a":0,"k":{"c":true,"i":[[0,0],[0,0],[-1.015,-0.1],[-10.635,-13.841],[-12.536,-101.377],[0,0],[0.956,-0.932],[0,0]],"o":[[0,0],[0.04,-1.02],[23.499,2.367],[10.755,13.997],[0,0],[1.272,0.407],[0,0],[0,0]],"v":[[-78.446,26.328],[-71.571,-145.183],[-69.623,-146.876],[-17.446,-122.1],[4.42,1.822],[77.214,25.151],[77.91,28.108],[12.987,91.351]]},"ix":2}},{"ty":"fl","bm":0,"hd":false,"mn":"ADBE Vector Graphic - Fill","nm":"Fill 1","c":{"a":0,"k":[0.1608,0.1725,0.3373],"ix":4},"r":1,"o":{"a":0,"k":100,"ix":5}},{"ty":"tr","a":{"a":0,"k":[0,0],"ix":1},"s":{"a":0,"k":[100,100],"ix":3},"sk":{"a":0,"k":0,"ix":4},"p":{"a":0,"k":[402.23,368.445],"ix":2},"r":{"a":0,"k":0,"ix":6},"sa":{"a":0,"k":0,"ix":5},"o":{"a":0,"k":100,"ix":7}}]},{"ty":"gr","bm":0,"hd":false,"mn":"ADBE Vector Group","nm":"Group 2","ix":2,"cix":2,"np":2,"it":[{"ty":"sh","bm":0,"hd":false,"mn":"ADBE Vector Shape - Group","nm":"Path 1","ix":1,"d":1,"ks":{"a":0,"k":{"c":true,"i":[[-21.94,21.372],[24.625,7.891],[10.481,13.64],[14.158,1.426],[2.292,-57.171],[-5.958,-4.463]],"o":[[-24.625,-7.891],[-12.569,-101.551],[-13.777,-17.93],[-2.292,57.17],[15.445,9.531],[21.94,-21.372]],"v":[[76.674,26.835],[2.8,3.16],[-18.851,-121.024],[-69.8,-145.116],[-76.674,24.395],[13.041,87.577]]},"ix":2}},{"ty":"fl","bm":0,"hd":false,"mn":"ADBE Vector Graphic - Fill","nm":"Fill 1","c":{"a":0,"k":[1,1,1],"ix":4},"r":1,"o":{"a":0,"k":100,"ix":5}},{"ty":"tr","a":{"a":0,"k":[0,0],"ix":1},"s":{"a":0,"k":[100,100],"ix":3},"sk":{"a":0,"k":0,"ix":4},"p":{"a":0,"k":[402.229,368.449],"ix":2},"r":{"a":0,"k":0,"ix":6},"sa":{"a":0,"k":0,"ix":5},"o":{"a":0,"k":100,"ix":7}}]},{"ty":"tr","a":{"a":0,"k":[402.229,368.449],"ix":1},"s":{"a":0,"k":[100,100],"ix":3},"sk":{"a":0,"k":0,"ix":4},"p":{"a":0,"k":[402.229,368.449],"ix":2},"r":{"a":0,"k":0,"ix":6},"sa":{"a":0,"k":0,"ix":5},"o":{"a":0,"k":100,"ix":7}}]}],"ind":7,"parent":4},{"ty":4,"nm":"Examination 2","sr":1,"st":0,"op":180,"ip":0,"hd":false,"ddd":0,"bm":0,"hasMask":false,"ao":0,"ks":{"a":{"a":0,"k":[746.03,524.356,0],"ix":1},"s":{"a":0,"k":[100,100,100],"ix":6},"sk":{"a":0,"k":0},"p":{"a":0,"k":[1273.1123196939848,508.356],"ix":2},"r":{"a":0,"k":0,"ix":10},"sa":{"a":0,"k":0},"o":{"a":0,"k":100,"ix":11}},"shapes":[{"ty":"gr","bm":0,"hd":false,"mn":"ADBE Vector Group","nm":"Group 1","ix":1,"cix":2,"np":4,"it":[{"ty":"sh","bm":0,"hd":false,"mn":"ADBE Vector Shape - Group","nm":"Path 1","ix":1,"d":1,"ks":{"a":0,"k":{"c":true,"i":[[0,0],[0,0]],"o":[[0,0],[0,0]],"v":[[85.918,238.819],[85.935,238.819]]},"ix":2}},{"ty":"sh","bm":0,"hd":false,"mn":"ADBE Vector Shape - Group","nm":"Path 2","ix":2,"d":1,"ks":{"a":0,"k":{"c":true,"i":[[-30.978,0],[-6.316,-2.017],[2.191,-65.585],[0.806,-4.529],[-14.718,13.703],[-11.696,28.025],[1.604,41.5],[-21.628,32.817],[1.142,24.338],[58.281,2.477],[22.598,-29.693],[0.672,0.881],[37.297,-1.575],[2.945,-58.013],[-10.648,-18.786],[1.715,-36.893],[0.036,-0.916],[-53.498,-68.04],[-1.084,19.7],[-11.68,25.724]],"o":[[5.382,0],[32.133,10.265],[-0.65,4.968],[-3.187,17.928],[23.651,-23.651],[13.155,-31.522],[-1.562,-40.46],[13.304,-20.187],[-2.731,-58.259],[-37.301,-1.573],[-0.672,0.881],[-22.599,-29.692],[-58.056,2.467],[-1.106,21.779],[19.336,34.116],[-0.044,0.944],[-1.765,44.64],[13.207,16.743],[2.337,-42.488],[0.219,-0.42]],"v":[[-8.545,88.718],[8.995,91.595],[54.117,205.904],[51.931,220.129],[84.704,237.527],[138.743,156.921],[156.152,46.873],[187.267,-66.759],[205.86,-134.817],[97.054,-243.129],[1.41,-198.238],[-1.412,-198.238],[-97.055,-243.129],[-205.84,-135.273],[-191.254,-73.265],[-164.32,35.277],[-164.44,38.069],[-115.993,233.841],[-76.675,221.934],[-55.25,117.669]]},"ix":2}},{"ty":"sh","bm":0,"hd":false,"mn":"ADBE Vector Shape - Group","nm":"Path 3","ix":3,"d":1,"ks":{"a":0,"k":{"c":true,"i":[[-3.875,21.79],[-0.629,4.743],[30.437,9.723],[0.807,-1.515],[2.313,-42.051],[15.267,19.351],[-1.784,45.095],[-0.044,0.953],[19.006,33.533],[-1.141,22.454],[-59.865,2.543],[-23.361,-29.482],[-37.683,-1.612],[-2.816,-60.074],[13.72,-20.817],[-1.535,-39.727],[13.355,-32.001],[17.894,-16.671]],"o":[[0.796,-4.477],[2.118,-63.634],[-39.79,-12.716],[-11.451,25.23],[-1.263,22.966],[-54.307,-69.069],[0.036,-0.925],[1.684,-36.225],[-10.98,-19.374],[3.036,-59.822],[37.695,-1.599],[23.361,-29.484],[60.098,2.554],[1.176,25.092],[-21.223,32.204],[1.623,42.019],[-14.066,33.703],[-16.103,14.921]],"v":[[48.441,219.508],[50.588,205.612],[7.916,94.972],[-52.071,119.232],[-73.135,222.128],[-118.778,236.034],[-167.982,37.93],[-167.862,35.113],[-194.339,-71.517],[-209.38,-135.453],[-97.206,-246.67],[-0.001,-202.201],[97.204,-246.67],[209.401,-134.983],[190.227,-64.808],[159.695,46.736],[142.014,158.286],[86.576,240.628]]},"ix":2}},{"ty":"fl","bm":0,"hd":false,"mn":"ADBE Vector Graphic - Fill","nm":"Fill 1","c":{"a":0,"k":[0.1608,0.1725,0.3373],"ix":4},"r":1,"o":{"a":0,"k":100,"ix":5}},{"ty":"tr","a":{"a":0,"k":[0,0],"ix":1},"s":{"a":0,"k":[100,100],"ix":3},"sk":{"a":0,"k":0,"ix":4},"p":{"a":0,"k":[746.03,524.356],"ix":2},"r":{"a":0,"k":0,"ix":6},"sa":{"a":0,"k":0,"ix":5},"o":{"a":0,"k":100,"ix":7}}]},{"ty":"gr","bm":0,"hd":false,"mn":"ADBE Vector Group","nm":"Group 2","ix":2,"cix":2,"np":2,"it":[{"ty":"sh","bm":0,"hd":false,"mn":"ADBE Vector Shape - Group","nm":"Path 1","ix":1,"d":1,"ks":{"a":0,"k":{"c":true,"i":[[1.2,25.586],[59.416,2.525],[22.069,-28.998],[39.626,-1.683],[3.006,-59.219],[-10.447,-18.432],[1.752,-37.678],[0.036,-0.921],[-53.902,-68.553],[-1.169,21.26],[-11.487,25.3],[-41.633,-13.299],[1.3,-38.9],[0.842,-4.736],[-15.857,14.789],[-20.768,49.763],[1.365,35.329],[-21.903,33.234]],"o":[[-2.785,-59.404],[-39.627,-1.684],[-22.069,-28.997],[-59.242,2.516],[-1.165,22.956],[18.599,32.815],[-0.044,0.949],[-1.751,44.278],[14.223,18.079],[2.346,-42.668],[0.08,-0.151],[41.698,13.32],[-0.607,4.584],[-3.512,19.748],[0,0],[15.137,-36.27],[-1.536,-39.772],[12.963,-19.67]],"v":[[207.632,-134.885],[97.131,-244.884],[0,-199.295],[-97.129,-244.884],[-207.609,-135.348],[-192.795,-72.375],[-166.089,35.21],[-166.21,38.015],[-117.385,234.952],[-74.904,222.047],[-53.635,118.418],[8.457,93.3],[52.347,205.86],[50.187,219.834],[85.919,238.835],[140.38,157.619],[157.925,46.821],[188.749,-65.768]]},"ix":2}},{"ty":"fl","bm":0,"hd":false,"mn":"ADBE Vector Graphic - Fill","nm":"Fill 1","c":{"a":0,"k":[1,1,1],"ix":4},"r":1,"o":{"a":0,"k":100,"ix":5}},{"ty":"tr","a":{"a":0,"k":[0,0],"ix":1},"s":{"a":0,"k":[100,100],"ix":3},"sk":{"a":0,"k":0,"ix":4},"p":{"a":0,"k":[746.028,524.34],"ix":2},"r":{"a":0,"k":0,"ix":6},"sa":{"a":0,"k":0,"ix":5},"o":{"a":0,"k":100,"ix":7}}]}],"ind":8},{"ty":0,"nm":"Nested Scene 2","sr":1,"st":0,"op":121,"ip":0,"hd":false,"ddd":0,"bm":0,"hasMask":false,"ao":0,"ks":{"a":{"a":0,"k":[241.50003183339027,86.50003183339032]},"s":{"a":0,"k":[386.47880510370686,386.478805103707]},"sk":{"a":0,"k":0},"p":{"a":0,"k":[1050.6400445909292,449.3164070529312]},"r":{"a":0,"k":0},"sa":{"a":0,"k":0},"o":{"a":0,"k":100}},"w":483,"h":173,"refId":"precomp_Shape Layer - SVG_D5dGc4Ed2j_f7aba981-672a-462f-b540-d37694b36301_23b72739-c4af-4558-ba7e-7e699d48c71b","ind":9},{"ty":0,"nm":"Nested Scene 1","sr":1,"st":0,"op":121,"ip":0,"hd":true,"ddd":0,"bm":0,"hasMask":false,"ao":0,"ks":{"a":{"a":0,"k":[241.49996636446122,86.4999931279974]},"s":{"a":0,"k":[411.16248325060394,411.1624832506041]},"sk":{"a":0,"k":0},"p":{"a":0,"k":[1483.3530356894928,391.00208541545743]},"r":{"a":0,"k":0},"sa":{"a":0,"k":0},"o":{"a":0,"k":100}},"w":483,"h":173,"refId":"precomp_Shape Layer - SVG_-asql2bpdg_e87bb237-4176-4c2c-bce1-35bcb40aca2b_c9d607b5-2f03-4365-9058-98de9a684f35","ind":10},{"ty":4,"nm":"Examination","sr":1,"st":0,"op":180,"ip":0,"hd":true,"ddd":0,"bm":0,"hasMask":false,"ao":0,"ks":{"a":{"a":0,"k":[0,0,0],"ix":1},"s":{"a":0,"k":[100,100,100],"ix":6},"sk":{"a":0,"k":0},"p":{"a":0,"k":[929.7453196939848,396.099],"ix":2},"r":{"a":0,"k":0,"ix":10},"sa":{"a":0,"k":0},"o":{"a":0,"k":100,"ix":11}},"shapes":[{"ty":"gr","bm":0,"hd":false,"mn":"ADBE Vector Group","nm":"Group 1","ix":1,"cix":2,"np":2,"it":[{"ty":"sh","bm":0,"hd":false,"mn":"ADBE Vector Shape - Group","nm":"Path 1","ix":1,"d":1,"ks":{"a":0,"k":{"c":true,"i":[[0,0],[0,0],[0,0],[0,0],[0,0],[0,0],[0,0],[0,0],[0,0],[0,0],[0,0],[0,0]],"o":[[0,0],[0,0],[0,0],[0,0],[0,0],[0,0],[0,0],[0,0],[0,0],[0,0],[0,0],[0,0]],"v":[[108.791,-108.791],[108.791,-276.065],[-108.791,-276.065],[-108.791,-108.791],[-276.065,-108.791],[-276.065,108.791],[-108.791,108.791],[-108.791,276.065],[108.791,276.065],[108.791,108.791],[276.065,108.791],[276.065,-108.791]]},"ix":2}},{"ty":"fl","bm":0,"hd":false,"mn":"ADBE Vector Graphic - Fill","nm":"Fill 1","c":{"a":0,"k":[0.8627,0.9059,0.9176],"ix":4},"r":1,"o":{"a":0,"k":100,"ix":5}},{"ty":"tr","a":{"a":0,"k":[0,0],"ix":1},"s":{"a":0,"k":[100,100],"ix":3},"sk":{"a":0,"k":0,"ix":4},"p":{"a":0,"k":[0,0],"ix":2},"r":{"a":0,"k":0,"ix":6},"sa":{"a":0,"k":0,"ix":5},"o":{"a":0,"k":100,"ix":7}}]}],"ind":11}],"v":"5.7.0","fr":30,"op":121,"ip":0,"assets":[{"nm":"Nested Scene 1","id":"precomp_Shape Layer - SVG_-asql2bpdg_e87bb237-4176-4c2c-bce1-35bcb40aca2b_c9d607b5-2f03-4365-9058-98de9a684f35","fr":30,"layers":[{"ty":4,"nm":"Shape Layer 1","sr":1,"st":0,"op":121,"ip":0,"hd":false,"ddd":0,"bm":0,"hasMask":false,"ao":0,"ks":{"a":{"a":0,"k":[241.075040538875,86.25002216452827]},"s":{"a":0,"k":[100,100]},"sk":{"a":0,"k":0},"p":{"a":0,"k":[241.075040538875,86.25002216452827]},"r":{"a":0,"k":0},"sa":{"a":0,"k":0},"o":{"a":0,"k":100}},"shapes":[{"ty":"gr","bm":0,"hd":false,"nm":"Group 1","np":3,"it":[{"ty":"sh","bm":0,"hd":false,"nm":"Path 1","d":1,"ks":{"a":0,"k":{"c":true,"i":[[0,0],[4.42,0],[0,0],[0,4.42],[0,0],[-1.08,1.4],[0,0],[-2.48,0],[0,0],[2.93,-5.33],[0,0],[1.66,0],[0.86,-1.17],[0,0],[0,-0.36],[-0.94,0],[0,0],[0,-4.42],[0,0]],"o":[[0,4.42],[0,0],[-4.42,0],[0,0],[0,-1.77],[0,0],[1.51,-1.96],[0,0],[6.08,0],[0,0],[-0.8,1.46],[-1.45,0],[0,0],[-0.21,0.29],[0,0.94],[0,0],[4.42,0],[0,0],[0,0]],"v":[[157.25,132.75],[149.25,140.75],[8,140.75],[0,132.75],[0,109.23],[1.67,104.34],[77.85,5.61],[84.18,2.5],[107.47,2.5],[114.48,14.36],[92.05,55.14],[88.06,57.5],[84.38,59.36],[57.58,95.8],[57.25,96.81],[58.94,98.5],[149.25,98.5],[157.25,106.5],[157.25,132.75]]}}},{"ty":"sh","bm":0,"hd":false,"nm":"Path 2","d":1,"ks":{"a":0,"k":{"c":true,"i":[[0,0],[4.42,0],[0,0],[0,4.42],[0,0],[-4.42,0],[0,0],[0,-4.42],[0,0]],"o":[[0,4.42],[0,0],[-4.42,0],[0,0],[0,-4.42],[0,0],[4.42,0],[0,0],[0,0]],"v":[[134.75,162],[126.75,170],[96,170],[88,162],[88,10.5],[96,2.5],[126.75,2.5],[134.75,10.5],[134.75,162]]}}},{"ty":"fl","bm":0,"hd":false,"nm":"Fill","c":{"a":0,"k":[0.851,0.851,0.851]},"r":1,"o":{"a":0,"k":100}},{"ty":"tr","a":{"a":0,"k":[78.62501564276931,86.25002216452827]},"s":{"a":0,"k":[100,100]},"sk":{"a":0,"k":0},"p":{"a":0,"k":[78.62501564276931,86.25002216452827]},"r":{"a":0,"k":0},"sa":{"a":0,"k":0},"o":{"a":0,"k":100}}]},{"ty":"gr","bm":0,"hd":false,"nm":"Group 2","np":3,"it":[{"ty":"sh","bm":0,"hd":false,"nm":"Path 3","d":1,"ks":{"a":0,"k":{"c":true,"i":[[0,0],[11.67,7.17],[5.83,12.83],[0,17.17],[-5.83,12.83],[-11.5,7.17],[-17,0],[-11.5,-7.33],[-5.83,-13],[0,-17.17],[5.83,-13],[11.67,-7.33],[17,0]],"o":[[-17,0],[-11.5,-7.33],[-5.83,-13],[0,-17.17],[5.83,-13],[11.67,-7.33],[17,0],[11.67,7.17],[5.83,12.83],[0,17.17],[-5.83,12.83],[-11.5,7.17],[0,0]],"v":[[240.14,172.5],[197.14,161.75],[171.14,131.5],[162.39,86.25],[171.14,41.25],[197.14,11],[240.14,0],[282.89,11],[309.14,41.25],[317.89,86.25],[309.14,131.5],[282.89,161.75],[240.14,172.5]]}}},{"ty":"sh","bm":0,"hd":false,"nm":"Path 4","d":1,"ks":{"a":0,"k":{"c":true,"i":[[0,0],[-3.83,1.83],[-1.5,5.83],[0,11.5],[1.67,5.67],[4,1.83],[7.17,0],[4,-2],[1.5,-5.83],[0,-11.67],[-1.5,-5.83],[-4,-2],[-7.17,0]],"o":[[7.17,0],[4,-2],[1.67,-5.83],[0,-11.67],[-1.5,-5.83],[-3.83,-2],[-7.17,0],[-4,1.83],[-1.5,5.67],[0,11.5],[1.5,5.83],[4,1.83],[0,0]],"v":[[240.14,126.75],[256.64,124],[264.89,112.25],[267.39,86.25],[264.89,60.25],[256.64,48.75],[240.14,45.75],[223.39,48.75],[215.14,60.25],[212.89,86.25],[215.14,112.25],[223.39,124],[240.14,126.75]]}}},{"ty":"fl","bm":0,"hd":false,"nm":"Fill","c":{"a":0,"k":[0.851,0.851,0.851]},"r":1,"o":{"a":0,"k":100}},{"ty":"tr","a":{"a":0,"k":[240.14006110415454,86.25002216452827]},"s":{"a":0,"k":[100,100]},"sk":{"a":0,"k":0},"p":{"a":0,"k":[240.14006110415454,86.25002216452827]},"r":{"a":0,"k":0},"sa":{"a":0,"k":0},"o":{"a":0,"k":100}}]},{"ty":"gr","bm":0,"hd":false,"nm":"Group 3","np":3,"it":[{"ty":"sh","bm":0,"hd":false,"nm":"Path 5","d":1,"ks":{"a":0,"k":{"c":true,"i":[[0,0],[4.42,0],[0,0],[0,4.42],[0,0],[-1.08,1.4],[0,0],[-2.48,0],[0,0],[2.93,-5.33],[0,0],[1.66,0],[0.86,-1.17],[0,0],[0,-0.36],[-0.93,0],[0,0],[0,-4.42],[0,0]],"o":[[0,4.42],[0,0],[-4.42,0],[0,0],[0,-1.77],[0,0],[1.51,-1.96],[0,0],[6.09,0],[0,0],[-0.8,1.46],[-1.45,0],[0,0],[-0.21,0.29],[0,0.94],[0,0],[4.42,0],[0,0],[0,0]],"v":[[482.15,132.75],[474.15,140.75],[332.9,140.75],[324.9,132.75],[324.9,109.23],[326.57,104.34],[402.75,5.61],[409.09,2.5],[432.37,2.5],[439.38,14.36],[416.95,55.14],[412.96,57.5],[409.29,59.36],[382.48,95.8],[382.15,96.81],[383.85,98.5],[474.15,98.5],[482.15,106.5],[482.15,132.75]]}}},{"ty":"sh","bm":0,"hd":false,"nm":"Path 6","d":1,"ks":{"a":0,"k":{"c":true,"i":[[0,0],[4.42,0],[0,0],[0,4.42],[0,0],[-4.42,0],[0,0],[0,-4.42],[0,0]],"o":[[0,4.42],[0,0],[-4.42,0],[0,0],[0,-4.42],[0,0],[4.42,0],[0,0],[0,0]],"v":[[459.65,162],[451.65,170],[420.9,170],[412.9,162],[412.9,10.5],[420.9,2.5],[451.65,2.5],[459.65,10.5],[459.65,162]]}}},{"ty":"fl","bm":0,"hd":false,"nm":"Fill","c":{"a":0,"k":[0.851,0.851,0.851]},"r":1,"o":{"a":0,"k":100}},{"ty":"tr","a":{"a":0,"k":[403.52503684321164,86.25002216452827]},"s":{"a":0,"k":[100,100]},"sk":{"a":0,"k":0},"p":{"a":0,"k":[403.52503684321164,86.25002216452827]},"r":{"a":0,"k":0},"sa":{"a":0,"k":0},"o":{"a":0,"k":100}}]}],"ind":1}]},{"nm":"Nested Scene 2","id":"precomp_Shape Layer - SVG_D5dGc4Ed2j_f7aba981-672a-462f-b540-d37694b36301_23b72739-c4af-4558-ba7e-7e699d48c71b","fr":30,"layers":[{"ty":4,"nm":"Shape Layer 1","sr":1,"st":0,"op":121,"ip":0,"hd":false,"ddd":0,"bm":0,"hasMask":false,"ao":0,"ks":{"a":{"a":0,"k":[241.0749924055342,86.25001238563851]},"s":{"a":0,"k":[100,100]},"sk":{"a":0,"k":0},"p":{"a":0,"k":[241.92499734502945,86.75002068561002]},"r":{"a":0,"k":0},"sa":{"a":0,"k":0},"o":{"a":0,"k":100}},"shapes":[{"ty":"gr","bm":0,"hd":false,"nm":"Group 1","np":3,"it":[{"ty":"sh","bm":0,"hd":false,"nm":"Path 1","d":1,"ks":{"a":0,"k":{"c":true,"i":[[0,0],[4.42,0],[0,0],[0,4.42],[0,0],[-1.08,1.4],[0,0],[-2.48,0],[0,0],[2.93,-5.33],[0,0],[1.66,0],[0.86,-1.17],[0,0],[0,-0.36],[-0.94,0],[0,0],[0,-4.42],[0,0]],"o":[[0,4.42],[0,0],[-4.42,0],[0,0],[0,-1.77],[0,0],[1.51,-1.96],[0,0],[6.08,0],[0,0],[-0.8,1.46],[-1.45,0],[0,0],[-0.21,0.29],[0,0.94],[0,0],[4.42,0],[0,0],[0,0]],"v":[[157.25,132.75],[149.25,140.75],[8,140.75],[0,132.75],[0,109.23],[1.67,104.34],[77.85,5.61],[84.18,2.5],[107.47,2.5],[114.48,14.36],[92.05,55.14],[88.06,57.5],[84.38,59.36],[57.58,95.8],[57.25,96.81],[58.94,98.5],[149.25,98.5],[157.25,106.5],[157.25,132.75]]}}},{"ty":"sh","bm":0,"hd":false,"nm":"Path 2","d":1,"ks":{"a":0,"k":{"c":true,"i":[[0,0],[4.42,0],[0,0],[0,4.42],[0,0],[-4.42,0],[0,0],[0,-4.42],[0,0]],"o":[[0,4.42],[0,0],[-4.42,0],[0,0],[0,-4.42],[0,0],[4.42,0],[0,0],[0,0]],"v":[[134.75,162],[126.75,170],[96,170],[88,162],[88,10.5],[96,2.5],[126.75,2.5],[134.75,10.5],[134.75,162]]}}},{"ty":"fl","bm":0,"hd":false,"nm":"Fill","c":{"a":0,"k":[0,0.4,1]},"r":1,"o":{"a":0,"k":25}},{"ty":"tr","a":{"a":0,"k":[78.62499947904644,86.25001238563851]},"s":{"a":0,"k":[100,100]},"sk":{"a":0,"k":0},"p":{"a":0,"k":[78.62499947904644,86.25001238563851]},"r":{"a":0,"k":0},"sa":{"a":0,"k":0},"o":{"a":0,"k":100}}]},{"ty":"gr","bm":0,"hd":false,"nm":"Group 2","np":3,"it":[{"ty":"sh","bm":0,"hd":false,"nm":"Path 3","d":1,"ks":{"a":0,"k":{"c":true,"i":[[0,0],[11.67,7.17],[5.83,12.83],[0,17.17],[-5.83,12.83],[-11.5,7.17],[-17,0],[-11.5,-7.33],[-5.83,-13],[0,-17.17],[5.83,-13],[11.67,-7.33],[17,0]],"o":[[-17,0],[-11.5,-7.33],[-5.83,-13],[0,-17.17],[5.83,-13],[11.67,-7.33],[17,0],[11.67,7.17],[5.83,12.83],[0,17.17],[-5.83,12.83],[-11.5,7.17],[0,0]],"v":[[240.14,172.5],[197.14,161.75],[171.14,131.5],[162.39,86.25],[171.14,41.25],[197.14,11],[240.14,0],[282.89,11],[309.14,41.25],[317.89,86.25],[309.14,131.5],[282.89,161.75],[240.14,172.5]]}}},{"ty":"sh","bm":0,"hd":false,"nm":"Path 4","d":1,"ks":{"a":0,"k":{"c":true,"i":[[0,0],[-3.83,1.83],[-1.5,5.83],[0,11.5],[1.67,5.67],[4,1.83],[7.17,0],[4,-2],[1.5,-5.83],[0,-11.67],[-1.5,-5.83],[-4,-2],[-7.17,0]],"o":[[7.17,0],[4,-2],[1.67,-5.83],[0,-11.67],[-1.5,-5.83],[-3.83,-2],[-7.17,0],[-4,1.83],[-1.5,5.67],[0,11.5],[1.5,5.83],[4,1.83],[0,0]],"v":[[240.14,126.75],[256.64,124],[264.89,112.25],[267.39,86.25],[264.89,60.25],[256.64,48.75],[240.14,45.75],[223.39,48.75],[215.14,60.25],[212.89,86.25],[215.14,112.25],[223.39,124],[240.14,126.75]]}}},{"ty":"fl","bm":0,"hd":false,"nm":"Fill","c":{"a":0,"k":[0,0.4,1]},"r":1,"o":{"a":0,"k":25}},{"ty":"tr","a":{"a":0,"k":[240.1399502309971,86.25001238563851]},"s":{"a":0,"k":[100,100]},"sk":{"a":0,"k":0},"p":{"a":0,"k":[240.64993666560466,86.25000408566703]},"r":{"a":0,"k":0},"sa":{"a":0,"k":0},"o":{"a":0,"k":100}}]},{"ty":"gr","bm":0,"hd":false,"nm":"Group 3","np":3,"it":[{"ty":"sh","bm":0,"hd":false,"nm":"Path 5","d":1,"ks":{"a":0,"k":{"c":true,"i":[[0,0],[4.42,0],[0,0],[0,4.42],[0,0],[-1.08,1.4],[0,0],[-2.48,0],[0,0],[2.93,-5.33],[0,0],[1.66,0],[0.86,-1.17],[0,0],[0,-0.36],[-0.93,0],[0,0],[0,-4.42],[0,0]],"o":[[0,4.42],[0,0],[-4.42,0],[0,0],[0,-1.77],[0,0],[1.51,-1.96],[0,0],[6.09,0],[0,0],[-0.8,1.46],[-1.45,0],[0,0],[-0.21,0.29],[0,0.94],[0,0],[4.42,0],[0,0],[0,0]],"v":[[482.15,132.75],[474.15,140.75],[332.9,140.75],[324.9,132.75],[324.9,109.23],[326.57,104.34],[402.75,5.61],[409.09,2.5],[432.37,2.5],[439.38,14.36],[416.95,55.14],[412.96,57.5],[409.29,59.36],[382.48,95.8],[382.15,96.81],[383.85,98.5],[474.15,98.5],[482.15,106.5],[482.15,132.75]]}}},{"ty":"sh","bm":0,"hd":false,"nm":"Path 6","d":1,"ks":{"a":0,"k":{"c":true,"i":[[0,0],[4.42,0],[0,0],[0,4.42],[0,0],[-4.42,0],[0,0],[0,-4.42],[0,0]],"o":[[0,4.42],[0,0],[-4.42,0],[0,0],[0,-4.42],[0,0],[4.42,0],[0,0],[0,0]],"v":[[459.65,162],[451.65,170],[420.9,170],[412.9,162],[412.9,10.5],[420.9,2.5],[451.65,2.5],[459.65,10.5],[459.65,162]]}}},{"ty":"fl","bm":0,"hd":false,"nm":"Fill","c":{"a":0,"k":[0,0.4,1]},"r":1,"o":{"a":0,"k":25}},{"ty":"tr","a":{"a":0,"k":[403.5249534986315,86.25001238563851]},"s":{"a":0,"k":[100,100]},"sk":{"a":0,"k":0},"p":{"a":0,"k":[403.5249534986315,86.25001238563851]},"r":{"a":0,"k":0},"sa":{"a":0,"k":0},"o":{"a":0,"k":100}}]}],"ind":1}]}]}